Icarus/ex5/priority_encoders.v
/* reference referencedesigner.com */

`timescale 1ns / 100ps

module priory_encoder_case(x, pcode);

input wire [4:1] x;
output reg [2:0] pcode;

always @(*) begin
    case (x)
        4'b1000, 4'b1001, 4'b1010, 4'b1011, 4'b1100, 4'b1101, 4'b1110, 4'b1111:
        begin
            pcode = 3'b100;
        end
        4'b0100, 4'b0101, 4'b0110, 4'b0111:
        begin
            pcode = 3'b011;
        end
        4'b0010, 4'b0011:
        begin
            pcode = 3'b010;
        end
        4'b0001:
        begin
            pcode = 3'b001;
        end
        4'b0000: 
        begin
            pcode = 3'b000;
        end
    endcase
end

endmodule

Icarus/ex5/testbench_top.v
/* reference referencedesigner.com */

`timescale 1ns / 1ps
module top;
    reg [4:1] x;
    wire [2:0] pcode;

    priory_encoder_case uut (
        .x(x),
        .pcode(pcode)
    );

    initial begin
    $dumpfile("test.vcd");
    $dumpvars(0,top);

    x = 4'bzzzz;

    #20;

    for (x = 0; x < 15; x++) begin
        #20;
    end //for (x = 0; x < 15; x++) begin

    #20;

    $dumpflush;
    end //initial begin

    initial begin
    $monitor("t = %3d, x = %4b, pcode = %3b", $time, x, pcode);
    end //initial begin

endmodule

Icarus/ex5/test.vcd
$date
	Mon Sep 07 14:57:30 2020
$end
$version
	Icarus Verilog
$end
$timescale
	1ps
$end
$scope module top $end
$var wire 3 ! pcode [2:0] $end
$var reg 4 " x [4:1] $end
$scope module uut $end
$var wire 4 # x [4:1] $end
$var reg 3 $ pcode [2:0] $end
$upscope $end
$upscope $end
$enddefinitions $end
#0
$dumpvars
bx $
bz #
bz "
bx !
$end
#20000
b0 !
b0 $
b0 "
b0 #
#40000
b1 !
b1 $
b1 "
b1 #
#60000
b10 !
b10 $
b10 "
b10 #
#80000
b11 "
b11 #
#100000
b11 !
b11 $
b100 "
b100 #
#120000
b101 "
b101 #
#140000
b110 "
b110 #
#160000
b111 "
b111 #
#180000
b100 !
b100 $
b1000 "
b1000 #
#200000
b1001 "
b1001 #
#220000
b1010 "
b1010 #
#240000
b1011 "
b1011 #
#260000
b1100 "
b1100 #
#280000
b1101 "
b1101 #
#300000
b1110 "
b1110 #
#320000
b1111 "
b1111 #
