Icarus/ex17/wait_example.v
module wait_example();

reg mem_read, data_ready;
reg [7:0] data_bus, data;

always @ (mem_read or data_bus or data_ready)
begin
  data = 0;
  while (mem_read == 1'b1) begin
    // #1 is very important to avoid infinite loop
    //wait (data_ready == 1) #1 data = data_bus;
    wait (data_ready == 1) begin
        data = #1 data_bus;
        //#1 data = data_bus;
        data_ready = 0;
    end
  end
end

// Testbench Code here
initial begin
 $dumpfile("wave.vcd");
 $dumpvars(0,wait_example);
 $printtimescale;

 $monitor ("TIME = %g READ = %b READY = %b DATA = %b", 
   $time, mem_read, data_ready, data);
 data_bus = 0;
 mem_read = 0;
 data_ready = 0;
 #10 data_bus = 8'hDE;
 #10 mem_read = 1;
 #20 data_ready = 1;
 #1  mem_read = 1;
 //#1  data_ready = 0;
 #10 data_bus = 8'hAD;
 #10 mem_read = 1;
 #20 data_ready = 1;
 #1  mem_read = 1;
 //#1  data_ready = 0;
 #10 $finish;
end

endmodule

Icarus/ex17/wave.vcd
$date
	Wed Dec 30 02:12:34 2020
$end
$version
	Icarus Verilog
$end
$timescale
	1s
$end
$scope module wait_example $end
$var reg 8 ! data [7:0] $end
$var reg 8 " data_bus [7:0] $end
$var reg 1 # data_ready $end
$var reg 1 $ mem_read $end
$upscope $end
$enddefinitions $end
#0
$dumpvars
0$
0#
b0 "
b0 !
$end
#10
b11011110 "
#20
1$
#40
1#
#41
0#
b11011110 !
#51
b10101101 "
#81
1#
#82
0#
b10101101 !
