Icarus/ex10/my_ring_counter.v
/* reference referencedesigner.com */

`timescale 1ns / 100ps

module ring_counter #(parameter N = 4) (Clock, Reset, q);
input wire Clock, Reset;
output wire[N-1:0] q;

reg[N-1:0] next;

assign q = next;

always @(posedge Clock, negedge Reset) begin
    $display("N = %2d", N);

    if (!Reset) begin
        next <= {{(N-1){1'b0}}, {1'b1}};
    end else begin
        next <= next << 1;
        next[0] <= next[N-1];
    end
    //$display("time = %2d, \$display: r_reg=%b", $stime, r_reg);
end

endmodule

Icarus/ex10/testbench_top.v
/* reference referencedesigner.com */

`timescale 1ns / 100ps

module top;
reg Clock;
reg Reset;
parameter tbN = 8;
wire[tbN-1:0] q;
integer i;
//defparam uut.N = 6;

ring_counter #(.N(tbN)) uut (
.Clock(Clock),
.Reset(Reset),
.q(q)
);

initial begin
    $dumpfile("test.vcd");
    $dumpvars(0,top);
    $printtimescale;
    
    Reset = 1;

	#2 Reset = 0;
	#2 Reset = 1;

    $dumpflush;
end //initial begin

initial begin
    Clock = 0;

    for (i = 0; i <= 60; i = i+1) begin
       #10 Clock = ~Clock;
    end
end  
    
initial begin
$monitor("time = %2d, Clock = %d, Reset = %d, q = %4b",$time,Clock,Reset,q);
end

endmodule

Icarus/ex10/test.vcd
$date
	Tue Sep 08 17:22:00 2020
$end
$version
	Icarus Verilog
$end
$timescale
	100ps
$end
$scope module top $end
$var wire 8 ! q [7:0] $end
$var reg 1 " Clock $end
$var reg 1 # Reset $end
$var integer 32 $ i [31:0] $end
$scope module uut $end
$var wire 1 " Clock $end
$var wire 1 # Reset $end
$var wire 8 % q [7:0] $end
$var reg 8 & next [7:0] $end
$upscope $end
$upscope $end
$enddefinitions $end
#0
$dumpvars
bx &
bx %
b0 $
1#
0"
bx !
$end
#20
b1 !
b1 %
b1 &
0#
#40
1#
#100
b10 !
b10 %
b10 &
b1 $
1"
#200
b10 $
0"
#300
b100 !
b100 %
b100 &
b11 $
1"
#400
b100 $
0"
#500
b1000 !
b1000 %
b1000 &
b101 $
1"
#600
b110 $
0"
#700
b10000 !
b10000 %
b10000 &
b111 $
1"
#800
b1000 $
0"
#900
b100000 !
b100000 %
b100000 &
b1001 $
1"
#1000
b1010 $
0"
#1100
b1000000 !
b1000000 %
b1000000 &
b1011 $
1"
#1200
b1100 $
0"
#1300
b10000000 !
b10000000 %
b10000000 &
b1101 $
1"
#1400
b1110 $
0"
#1500
b1 !
b1 %
b1 &
b1111 $
1"
#1600
b10000 $
0"
#1700
b10 !
b10 %
b10 &
b10001 $
1"
#1800
b10010 $
0"
#1900
b100 !
b100 %
b100 &
b10011 $
1"
#2000
b10100 $
0"
#2100
b1000 !
b1000 %
b1000 &
b10101 $
1"
#2200
b10110 $
0"
#2300
b10000 !
b10000 %
b10000 &
b10111 $
1"
#2400
b11000 $
0"
#2500
b100000 !
b100000 %
b100000 &
b11001 $
1"
#2600
b11010 $
0"
#2700
b1000000 !
b1000000 %
b1000000 &
b11011 $
1"
#2800
b11100 $
0"
#2900
b10000000 !
b10000000 %
b10000000 &
b11101 $
1"
#3000
b11110 $
0"
#3100
b1 !
b1 %
b1 &
b11111 $
1"
#3200
b100000 $
0"
#3300
b10 !
b10 %
b10 &
b100001 $
1"
#3400
b100010 $
0"
#3500
b100 !
b100 %
b100 &
b100011 $
1"
#3600
b100100 $
0"
#3700
b1000 !
b1000 %
b1000 &
b100101 $
1"
#3800
b100110 $
0"
#3900
b10000 !
b10000 %
b10000 &
b100111 $
1"
#4000
b101000 $
0"
#4100
b100000 !
b100000 %
b100000 &
b101001 $
1"
#4200
b101010 $
0"
#4300
b1000000 !
b1000000 %
b1000000 &
b101011 $
1"
#4400
b101100 $
0"
#4500
b10000000 !
b10000000 %
b10000000 &
b101101 $
1"
#4600
b101110 $
0"
#4700
b1 !
b1 %
b1 &
b101111 $
1"
#4800
b110000 $
0"
#4900
b10 !
b10 %
b10 &
b110001 $
1"
#5000
b110010 $
0"
#5100
b100 !
b100 %
b100 &
b110011 $
1"
#5200
b110100 $
0"
#5300
b1000 !
b1000 %
b1000 &
b110101 $
1"
#5400
b110110 $
0"
#5500
b10000 !
b10000 %
b10000 &
b110111 $
1"
#5600
b111000 $
0"
#5700
b100000 !
b100000 %
b100000 &
b111001 $
1"
#5800
b111010 $
0"
#5900
b1000000 !
b1000000 %
b1000000 &
b111011 $
1"
#6000
b111100 $
0"
#6100
b10000000 !
b10000000 %
b10000000 &
b111101 $
1"
