Icarus/ex4/priority_encoders.v
/* Written by referencedesigner.com */

`timescale 1ns / 100ps

module priory_encoder_casez(A, pcode);

input wire [4:1] A;
output reg [2:0] pcode;

always @(*) begin
    casez (A)
        4'b1zzz:
        begin
            $display("casez 4'b1zzz");
            pcode = 3'b100;
        end
        4'b01zz:
        begin
            $display("casez 4'b01zz");
            pcode = 3'b011;
        end
        4'b001z:
        begin
            $display("casez 4'b001z");
            pcode = 3'b010;
        end
        4'b0001:
        begin
            $display("casez 4'b0001");
            pcode = 3'b001;
        end
        4'b0000:
        begin
            $display("casez 4'b0000");
            pcode = 3'b000;
        end
        default:
        begin
            $display("casez default");
            pcode = 3'b111;
        end
    endcase
end

endmodule

Icarus/ex4/testbench_top.v
/* Written by referencedesigner.com */

`timescale 1ns / 1ps
module top;
    reg [4:1] A;
    wire [2:0] pcode;

    priory_encoder_casez uut (
        .A(A),
        .pcode(pcode)
    );

    initial begin
    $dumpfile("test.vcd");
    $dumpvars(0,top);

    A = 4'b0000;

    #20 A = 4'b0001;
    #20 A = 4'b0010;
    #20 A = 4'b0011;
    #20 A = 4'b0100;
    #20 A = 4'b0101;  
    #20 A = 4'b0110;
    #20 A = 4'b0111;
    #20 A = 4'b1000;
    #20 A = 4'b1001;
    #20 A = 4'b1010;
    #20 A = 4'b1011;
    #20 A = 4'b1100;
    #20 A = 4'b1101;
    #20 A = 4'b1110;
    #20 A = 4'b1111;
    #40;
    $dumpflush;
    end

    initial begin
    $monitor("t = %3d, A = %4b, pcode = %3b", $time, A, pcode);
    end

endmodule

Icarus/ex4/test.vcd
$date
	Sun Sep 06 06:34:26 2020
$end
$version
	Icarus Verilog
$end
$timescale
	1ps
$end
$scope module top $end
$var wire 3 ! pcode [2:0] $end
$var reg 4 " A [4:1] $end
$scope module uut $end
$var wire 4 # A [4:1] $end
$var reg 3 $ pcode [2:0] $end
$upscope $end
$upscope $end
$enddefinitions $end
#0
$dumpvars
b0 $
b0 #
b0 "
b0 !
$end
#20000
b1 !
b1 $
b1 "
b1 #
#40000
b10 !
b10 $
b10 "
b10 #
#60000
b11 "
b11 #
#80000
b11 !
b11 $
b100 "
b100 #
#100000
b101 "
b101 #
#120000
b110 "
b110 #
#140000
b111 "
b111 #
#160000
b100 !
b100 $
b1000 "
b1000 #
#180000
b1001 "
b1001 #
#200000
b1010 "
b1010 #
#220000
b1011 "
b1011 #
#240000
b1100 "
b1100 #
#260000
b1101 "
b1101 #
#280000
b1110 "
b1110 #
#300000
b1111 "
b1111 #
