Icarus/ex7/mydff.v
/* reference referencedesigner.com */

`timescale 1ns / 100ps

module dff (Clock, D, Q);
input wire Clock;
input wire D;
output reg Q;

always @(posedge Clock) begin
    Q = D;
end

endmodule

Icarus/ex7/testbench_top.v
/* reference referencedesigner.com */

`timescale 1ns / 100ps

module top;
reg Clock;
reg D;
wire Q;
integer i;

dff uut (
.Clock(Clock),
.D(D),
.Q(Q)
);

initial begin
    $dumpfile("test.vcd");
    $dumpvars(0,top);

    D = 0;
    #8  D = 1;
    #10 D = 0;
    #10 D = 0;
    #10 D = 1;
    #10 D = 0;
    #10 D = 1;
    #40;

    $dumpflush;
end //initial begin

initial begin
    Clock = 0;

    for (i = 0; i <= 10; i = i+1) begin
       #10 Clock = ~Clock;
    end
end

initial begin
$monitor("time = %2d, Clock = %d, D = %d, Q = %d",$time,Clock,D,Q);
end

endmodule

Icarus/ex7/test.vcd
$date
	Mon Sep 07 14:56:28 2020
$end
$version
	Icarus Verilog
$end
$timescale
	100ps
$end
$scope module top $end
$var wire 1 ! Q $end
$var reg 1 " Clock $end
$var reg 1 # D $end
$var integer 32 $ i [31:0] $end
$scope module uut $end
$var wire 1 " Clock $end
$var wire 1 # D $end
$var reg 1 ! Q $end
$upscope $end
$upscope $end
$enddefinitions $end
#0
$dumpvars
b0 $
0#
0"
x!
$end
#80
1#
#100
1!
b1 $
1"
#180
0#
#200
b10 $
0"
#300
0!
b11 $
1"
#380
1#
#400
b100 $
0"
#480
0#
#500
b101 $
1"
#580
1#
#600
b110 $
0"
#700
1!
b111 $
1"
#800
b1000 $
0"
#900
b1001 $
1"
#1000
b1010 $
0"
#1100
b1011 $
1"
