Icarus/ex9/my_shift_reg.v
/* reference referencedesigner.com */

`timescale 1ns / 100ps

module shift_reg #(parameter N = 4) (Clock, Reset, S_IN, S_OUT);
input wire Clock, Reset;
input wire S_IN;
output wire S_OUT;

reg [N-1:0] r_reg;
wire [N-1:0] r_next;

assign r_next = {S_IN, r_reg[N-1:1]};
assign S_OUT = r_reg[0];

always @(posedge Clock, negedge Reset) begin
    if (!Reset) begin
        r_reg <= #1 0;
    end else begin
        r_reg <= r_next;
    end
    $display("time = %2d, \$display: r_reg=%b", $stime, r_reg);
end

endmodule

Icarus/ex9/testbench_top.v
/* reference referencedesigner.com */

`timescale 1ns / 100ps

module top;
reg Clock;
reg Reset;
reg S_IN;
wire S_OUT;
integer i;

shift_reg #(.N(10)) uut (
.Clock(Clock),
.Reset(Reset),
.S_IN(S_IN),
.S_OUT(S_OUT)
);

//shift_reg uut (
//.Clock(Clock),
//.Reset(Reset),
//.S_IN(S_IN),
//.S_OUT(S_OUT)
//);

initial begin
    $dumpfile("test.vcd");
    $dumpvars(0,top);
    $printtimescale;
    
    Reset = 1;
    S_IN = 0;

	#2 S_IN = 0; Reset = 0;
	#2 Reset = 1;
    
    for (i = 0; i <= 10; i = i + 1) begin
	    #20 S_IN = ~S_IN;
    end
    #20 S_IN = 1;
    #20 S_IN = 1;
    #20 S_IN = 0;
    #20 S_IN = 1;
    //#20 S_IN = 0;
    //#20 S_IN = 1;
    //#20 S_IN = 1;
    //#20 S_IN = 1;
    //#20 S_IN = 0;
	#40;

    $dumpflush;
end //initial begin

initial begin
    Clock = 0;

    for (i = 0; i <= 60; i = i+1) begin
       #10 Clock = ~Clock;
    end
end  
    
initial begin
$monitor("time = %2d, Clock = %d, Reset = %d, S_IN = %d, S_OUT = %d",$time,Clock,Reset,S_IN,S_OUT);
end

endmodule

Icarus/ex9/test.vcd
$date
	Mon Sep 07 16:39:12 2020
$end
$version
	Icarus Verilog
$end
$timescale
	100ps
$end
$scope module top $end
$var wire 1 ! S_OUT $end
$var reg 1 " Clock $end
$var reg 1 # Reset $end
$var reg 1 $ S_IN $end
$var integer 32 % i [31:0] $end
$scope module uut $end
$var wire 1 " Clock $end
$var wire 1 # Reset $end
$var wire 1 $ S_IN $end
$var wire 10 & r_next [9:0] $end
$var wire 1 ! S_OUT $end
$var reg 10 ' r_reg [9:0] $end
$upscope $end
$upscope $end
$enddefinitions $end
#0
$dumpvars
bx '
b0xxxxxxxxx &
b0 %
0$
1#
0"
x!
$end
#20
0#
#30
b0 &
0!
b0 '
#40
1#
#100
b1 %
1"
#200
b10 %
0"
#240
b11 %
b1000000000 &
1$
#300
b1100000000 &
b1000000000 '
b100 %
1"
#400
b101 %
0"
#440
b110 %
b100000000 &
0$
#500
b10000000 &
b100000000 '
b111 %
1"
#600
b1000 %
0"
#640
b1001 %
b1010000000 &
1$
#700
b1101000000 &
b1010000000 '
b1010 %
1"
#800
b1011 %
0"
#840
b1100 %
b101000000 &
0$
#900
b10100000 &
b101000000 '
b1101 %
1"
#1000
b1110 %
0"
#1040
b1010100000 &
1$
#1100
b1101010000 &
b1010100000 '
b1111 %
1"
#1200
b10000 %
0"
#1300
b1110101000 &
b1101010000 '
b10001 %
1"
#1400
b10010 %
0"
#1440
b110101000 &
0$
#1500
b11010100 &
b110101000 '
b10011 %
1"
#1600
b10100 %
0"
#1640
b1011010100 &
1$
#1700
b1101101010 &
b1011010100 '
b10101 %
1"
#1800
b10110 %
0"
#1900
b1110110101 &
b1101101010 '
b10111 %
1"
#2000
b11000 %
0"
#2100
b1111011010 &
1!
b1110110101 '
b11001 %
1"
#2200
b11010 %
0"
#2300
b1111101101 &
0!
b1111011010 '
b11011 %
1"
#2400
b11100 %
0"
#2500
b1111110110 &
1!
b1111101101 '
b11101 %
1"
#2600
b11110 %
0"
#2700
b1111111011 &
0!
b1111110110 '
b11111 %
1"
#2800
b100000 %
0"
#2900
b1111111101 &
1!
b1111111011 '
b100001 %
1"
#3000
b100010 %
0"
#3100
b1111111110 &
b1111111101 '
b100011 %
1"
#3200
b100100 %
0"
#3300
b1111111111 &
0!
b1111111110 '
b100101 %
1"
#3400
b100110 %
0"
#3500
1!
b1111111111 '
b100111 %
1"
#3600
b101000 %
0"
#3700
b101001 %
1"
#3800
b101010 %
0"
#3900
b101011 %
1"
#4000
b101100 %
0"
#4100
b101101 %
1"
#4200
b101110 %
0"
#4300
b101111 %
1"
#4400
b110000 %
0"
#4500
b110001 %
1"
#4600
b110010 %
0"
#4700
b110011 %
1"
#4800
b110100 %
0"
#4900
b110101 %
1"
#5000
b110110 %
0"
#5100
b110111 %
1"
#5200
b111000 %
0"
#5300
b111001 %
1"
#5400
b111010 %
0"
#5500
b111011 %
1"
#5600
b111100 %
0"
#5700
b111101 %
1"
