sync_fifo/sync_fifo.v
/************************************************************************************************************************
* FileName:    sync_fifo.v
* Author:      Yixing Shen 
* Description: Simple Sync FIFO
*
* History:
* 2021/01/13   Initial Version.
*
***********************************************************************************************************************/

`timescale 1 ns / 1 ps
`default_nettype none
`define dbg_wr_data_illegal

module sync_fifo
    #(
    parameter DATA_WIDTH = 8,
    parameter ADDR_WIDTH = 8
    )(
    clk,
    rst_n,
    wr_en,
    wr_full,
    wr_data,
    rd_en,
    rd_empty,
    rd_data,
    );    

    input wire clk;
    input wire rst_n;
    input wire wr_en;
    output wire wr_full;
    input wire [DATA_WIDTH-1:0] wr_data;
    input wire rd_en;
    output wire rd_empty;
    output reg [DATA_WIDTH-1:0] rd_data;

`ifdef dbg_wr_data_illegal
    reg [DATA_WIDTH-1:0] dbg_wr_data_illegal;
`endif
    reg [DATA_WIDTH-1:0] fifo_mem [(1 << ADDR_WIDTH)-1:0];
    reg [ADDR_WIDTH-1:0] wr_ptr;
    reg [ADDR_WIDTH-1:0] rd_ptr;
    reg [ADDR_WIDTH:0] qCount;
    wire enqueue;
    wire dequeue;

    assign wr_full  = (~rst_n) ? 1'b0 : (qCount == (1 << ADDR_WIDTH));
    assign rd_empty = (~rst_n) ? 1'b1 : (qCount == {ADDR_WIDTH{1'b0}});
    assign enqueue = wr_en && (~wr_full);
    assign dequeue = rd_en && (~rd_empty);

    always @(posedge clk or negedge rst_n) begin
        if (!rst_n) begin
            wr_ptr <= {ADDR_WIDTH{1'b0}};
            rd_ptr <= {ADDR_WIDTH{1'b0}};
            qCount <= {ADDR_WIDTH{1'b0}};
            rd_data <= {DATA_WIDTH{1'bz}};
        end
        else begin
            case ({enqueue,dequeue})
                2'b11: begin //enqueue,dequeue
                    rd_data <= fifo_mem[rd_ptr];
                    fifo_mem[wr_ptr] <= wr_data;
                end
                2'b10: begin //enqueue
                    fifo_mem[wr_ptr] <= wr_data;
                    rd_data <= {DATA_WIDTH{1'bz}};
                end
                2'b01: begin //dequeue
                    rd_data <= fifo_mem[rd_ptr];
                end
                default: begin //do nothing
                    rd_data <= {DATA_WIDTH{1'bz}};
`ifdef dbg_wr_data_illegal
                    dbg_wr_data_illegal <= wr_data;
`endif
                end
            endcase
            
            qCount <= qCount + (enqueue - dequeue);
            wr_ptr <= wr_ptr + enqueue;
            rd_ptr <= rd_ptr + dequeue;
        end
    end

endmodule

`resetall

sync_fifo/sync_fifo_tb.v
/************************************************************************************************************************
* FileName:    sync_fifo_tb.v
* Author:      Yixing Shen 
* Description: Simple Sync FIFO
*
* History:
* 2021/01/13   Initial Version.
*
***********************************************************************************************************************/

`timescale 1 ns / 1 ps
`default_nettype none

module syn_fifo_tb;
    parameter DATA_WIDTH = 8;
    parameter ADDR_WIDTH = 3;

    parameter DIR_WR    = 0;
    parameter DIR_RD    = 1;
    parameter DIR_WR_RD = 2;
    parameter DIR_CLOSE = 3;

    reg [DATA_WIDTH-1:0] data_out;
    wire [DATA_WIDTH-1:0] rd_data;
    reg [DATA_WIDTH-1:0] wr_data;
    wire wr_full;
    wire rd_empty;
    reg wr_en, clk, rst_n, rd_en;
    
    sync_fifo #(DATA_WIDTH,ADDR_WIDTH) sync_fifo_inst (.clk(clk),
                                                       .rst_n(rst_n),
                                                       .wr_en(wr_en),
                                                       .wr_full(wr_full),
                                                       .wr_data(wr_data), 
                                                       .rd_en(rd_en),
                                                       .rd_empty(rd_empty),
                                                       .rd_data(rd_data)
                                                      );

    initial begin
        rst_n = 0;
        clk = 0;
        wr_en = 0;
        rd_en = 0;
        #10;
        rst_n = 1;
        #10;
        dataTask(DIR_WR);
        dataTask(DIR_WR);
        dataTask(DIR_WR);
        dataTask(DIR_WR);
        dataTask(DIR_WR);
        dataTask(DIR_WR);
        dataTask(DIR_WR);
        dataTask(DIR_WR);

        dataTask(DIR_RD);
        dataTask(DIR_WR);
        dataTask(DIR_RD);
        dataTask(DIR_WR);
        dataTask(DIR_RD);
        dataTask(DIR_WR);
        #8;
        dataTask(DIR_WR_RD);
        dataTask(DIR_WR_RD);
        dataTask(DIR_WR_RD);
        dataTask(DIR_WR_RD);
        dataTask(DIR_WR_RD);
        dataTask(DIR_WR_RD);
        dataTask(DIR_WR_RD);
        dataTask(DIR_WR_RD);
        dataTask(DIR_WR_RD);
        dataTask(DIR_WR_RD);
        #8;
        dataTask(DIR_WR);
        dataTask(DIR_WR);
        dataTask(DIR_WR);
        dataTask(DIR_WR);
        dataTask(DIR_WR);
        dataTask(DIR_WR);
        dataTask(DIR_WR);
        dataTask(DIR_WR);
        #8;
        dataTask(DIR_WR);
        dataTask(DIR_WR);
        dataTask(DIR_WR);
        #8;
        dataTask(DIR_RD);
        dataTask(DIR_RD);
        dataTask(DIR_RD);
        dataTask(DIR_RD);
        dataTask(DIR_RD);
        dataTask(DIR_RD);
        dataTask(DIR_RD);
        dataTask(DIR_RD);
        #8;
        dataTask(DIR_RD);
        dataTask(DIR_RD);
        dataTask(DIR_RD);
    end

    initial begin
        $dumpfile("sim.vcd");
        $dumpvars(0,syn_fifo_tb);
        //$monitor("%4d %d %d 0x%x %d 0x%x", $time, clk, wr_full, wr_data, rd_empty, data_out);
        #800;
        $dumpflush;
        $finish;
    end

    task dataTask;
        input reg [1:0] dir;
        begin
            if (dir == DIR_WR) begin
                wr_en = 1;
                rd_en = 0;
                wr_data = ($random) % 256;
                $display("DIR_WR");
                $display("wr_full:%d,wr_data:0x%x",wr_full,wr_data);
                #2;
                clk = 1;
                #2;
                clk = 0;
                $display("rd_empty:%d,data_out:0x%x",rd_empty,data_out);
            end
            else if (dir == DIR_RD) begin 
                wr_en = 0;
                rd_en = 1;
                wr_data = 0;
                $display("DIR_RD");
                $display("wr_full:%d,wr_data:0x%x",wr_full,wr_data);
                #2;
                clk = 1;
                #2;
                clk = 0;
                data_out = rd_data;
                $display("rd_empty:%d,data_out:0x%x",rd_empty,data_out);
            end
            else if (dir == DIR_RD) begin 
                wr_en = 0;
                rd_en = 1;
                wr_data = 0;
                $display("DIR_RD");
                $display("wr_full:%d,wr_data:0x%x",wr_full,wr_data);
                #2;
                clk = 1;
                #2;
                clk = 0;
                data_out = rd_data;
                $display("rd_empty:%d,data_out:0x%x",rd_empty,data_out);
            end
            else if (dir == DIR_WR_RD) begin 
            end
            else begin
                wr_en = 0;
                rd_en = 0;
                wr_data = ($random) % 256;
                $display("DIR_CLOSE");
                $display("wr_full:%d,wr_data:0x%x",wr_full,wr_data);
                #2;
                clk = 1;
                #2;
                clk = 0;
                data_out = rd_data;
                $display("rd_empty:%d,data_out:0x%x",rd_empty,data_out);
            end
        end
    endtask

endmodule

`resetall

sync_fifo/sim.vcd
$date
	Wed Jan 13 13:10:28 2021
$end
$version
	Icarus Verilog
$end
$timescale
	1ps
$end
$scope module syn_fifo_tb $end
$var wire 1 ! wr_full $end
$var wire 1 " rd_empty $end
$var wire 8 # rd_data [7:0] $end
$var reg 1 $ clk $end
$var reg 8 % data_out [7:0] $end
$var reg 1 & rd_en $end
$var reg 1 ' rst_n $end
$var reg 8 ( wr_data [7:0] $end
$var reg 1 ) wr_en $end
$scope module sync_fifo_inst $end
$var wire 1 $ clk $end
$var wire 1 * dequeue $end
$var wire 1 + enqueue $end
$var wire 1 & rd_en $end
$var wire 1 ' rst_n $end
$var wire 8 , wr_data [7:0] $end
$var wire 1 ) wr_en $end
$var wire 1 ! wr_full $end
$var wire 1 " rd_empty $end
$var reg 8 - dbg_wr_data_illegal [7:0] $end
$var reg 4 . qCount [3:0] $end
$var reg 8 / rd_data [7:0] $end
$var reg 3 0 rd_ptr [2:0] $end
$var reg 3 1 wr_ptr [2:0] $end
$upscope $end
$scope task dataTask $end
$var reg 2 2 dir [1:0] $end
$upscope $end
$upscope $end
$enddefinitions $end
#0
$dumpvars
bx 2
b0 1
b0 0
bz /
b0 .
bx -
bx ,
0+
0*
0)
bx (
0'
0&
bx %
0$
bz #
1"
0!
$end
#10000
1'
#20000
1+
b100100 (
b100100 ,
1)
b0 2
#22000
0"
b1 1
b1 .
1$
#24000
b10000001 (
b10000001 ,
0$
#26000
b10 1
b10 .
1$
#28000
b1001 (
b1001 ,
0$
#30000
b11 1
b11 .
1$
#32000
b1100011 (
b1100011 ,
0$
#34000
b100 1
b100 .
1$
#36000
b1101 (
b1101 ,
0$
#38000
b101 1
b101 .
1$
#40000
b10001101 (
b10001101 ,
0$
#42000
b110 1
b110 .
1$
#44000
b1100101 (
b1100101 ,
0$
#46000
b111 1
b111 .
1$
#48000
b10010 (
b10010 ,
0$
#50000
0+
1!
b0 1
b1000 .
1$
#52000
1*
b0 (
b0 ,
1&
0)
b1 2
0$
#54000
0!
b1 0
b111 .
b100100 #
b100100 /
1$
#56000
0*
1+
b1 (
b1 ,
0&
1)
b0 2
b100100 %
0$
#58000
0+
1!
b1 1
b1000 .
bz #
bz /
1$
#60000
1*
b0 (
b0 ,
1&
0)
b1 2
0$
#62000
0!
b10 0
b111 .
b10000001 #
b10000001 /
1$
#64000
0*
1+
b1101 (
b1101 ,
0&
1)
b0 2
b10000001 %
0$
#66000
0+
1!
b10 1
b1000 .
bz #
bz /
1$
#68000
1*
b0 (
b0 ,
1&
0)
b1 2
0$
#70000
0!
b11 0
b111 .
b1001 #
b1001 /
1$
#72000
0*
1+
b1110110 (
b1110110 ,
0&
1)
b0 2
b1001 %
0$
#74000
0+
1!
b11 1
b1000 .
bz #
bz /
1$
#76000
0$
#84000
b10 2
#92000
b111101 (
b111101 ,
b0 2
#94000
b111101 -
1$
#96000
b11101101 (
b11101101 ,
0$
#98000
b11101101 -
1$
#100000
b10001100 (
b10001100 ,
0$
#102000
b10001100 -
1$
#104000
b11111001 (
b11111001 ,
0$
#106000
b11111001 -
1$
#108000
b11000110 (
b11000110 ,
0$
#110000
b11000110 -
1$
#112000
b11000101 (
b11000101 ,
0$
#114000
b11000101 -
1$
#116000
b10101010 (
b10101010 ,
0$
#118000
b10101010 -
1$
#120000
b11100101 (
b11100101 ,
0$
#122000
b11100101 -
1$
#124000
0$
#132000
b1110111 (
b1110111 ,
#134000
b1110111 -
1$
#136000
b10010 (
b10010 ,
0$
#138000
b10010 -
1$
#140000
b10001111 (
b10001111 ,
0$
#142000
b10001111 -
1$
#144000
0$
#152000
1*
b0 (
b0 ,
1&
0)
b1 2
#154000
0!
b100 0
b111 .
b1100011 #
b1100011 /
1$
#156000
b1100011 %
0$
#158000
b101 0
b110 .
b1101 #
b1101 /
1$
#160000
b1101 %
0$
#162000
b110 0
b101 .
b10001101 #
b10001101 /
1$
#164000
b10001101 %
0$
#166000
b111 0
b100 .
b1100101 #
b1100101 /
1$
#168000
b1100101 %
0$
#170000
b0 0
b11 .
b10010 #
b10010 /
1$
#172000
b10010 %
0$
#174000
b1 0
b10 .
b1 #
b1 /
1$
#176000
b1 %
0$
#178000
b10 0
b1 .
b1101 #
b1101 /
1$
#180000
b1101 %
0$
#182000
0*
1"
b11 0
b0 .
b1110110 #
b1110110 /
1$
#184000
b1110110 %
0$
#194000
b0 -
bz #
bz /
1$
#196000
bz %
0$
