Icarus/ex3/fulladder.v
/* Written by referencedesigner.com */

`timescale 1ns / 100ps

module fulladder
(
    input x,
    input y,
    input cin,

    output A, 
    output cout
);

assign {cout,A} = cin + y + x;

endmodule

Icarus/ex3/testbench_top.v
/* Written by referencedesigner.com */

`timescale 1ns / 100ps

module top; 

reg input1;
reg input2;
reg carryin;

wire out;
wire carryout;

fulladder uut (
    .x(input1),
    .y(input2),
    .cin(carryin),
    .A(out),
    .cout(carryout)
);

initial begin
    $dumpfile("test.vcd");
    $dumpvars(0,top);
    input1 = 0;
    input2 = 0;
    carryin = 0;

    #20; input1 = 0; input2 = 0;
    #20; input1 = 0; input2 = 1;
    #20; input1 = 1; input2 = 0;
    #20; input1 = 1; input2 = 1;
    #20; carryin = 1;
    #20; input1 = 0; input2 = 0;
    #20; input1 = 0; input2 = 1;
    #20; input1 = 1; input2 = 0;
    #20; input1 = 1; input2 = 1;
    #40;

    //#20; input1 = 1;
    //#20; input2 = 1;
    //#20; input1 = 0;
    //#20; carryin = 1;
    //#20; input2 = 0;
    //#20; input1 = 1;
    //#20; input2 = 1;
    //#40;
end

initial begin
$monitor("time = %2d, \tCIN = %1b, \tIN1 = %1b, \tIN2 = %1b, \tCOUT = %1b, \tOUT = %1b",$time,carryin,input2,input1,carryout,out);
end

endmodule

Icarus/ex3/test.vcd
$date
	Tue Sep 01 09:40:43 2020
$end
$version
	Icarus Verilog
$end
$timescale
	100ps
$end
$scope module top $end
$var wire 1 ! out $end
$var wire 1 " carryout $end
$var reg 1 # carryin $end
$var reg 1 $ input1 $end
$var reg 1 % input2 $end
$scope module uut $end
$var wire 1 # cin $end
$var wire 1 $ x $end
$var wire 1 % y $end
$var wire 1 " cout $end
$var wire 1 ! A $end
$upscope $end
$upscope $end
$enddefinitions $end
#0
$dumpvars
0%
0$
0#
0"
0!
$end
#400
1!
1%
#600
0%
1$
#800
0!
1"
1%
#1000
1!
1#
#1200
0"
0%
0$
#1400
0!
1"
1%
#1600
0%
1$
#1800
1!
1%
