uart/uart_rx.v
//20210116 UART RX

`timescale 1 ns / 1 ps
`default_nettype none

module uart_rx
    #(
    parameter SYS_CLOCK = 50000000,
    parameter UART_BAUDRATE = 115200
    )(
    input wire i_ResetN,
    input wire i_SysClock,
    input wire i_RxValid,
    output wire [7:0] o_RxByte,
    input wire i_RxSerial,
    output wire o_RxDone
    );

    parameter TIMER_COUNT_1 = (SYS_CLOCK / UART_BAUDRATE / 2);
    parameter TIMER_COUNT_2 = (SYS_CLOCK / UART_BAUDRATE);

    parameter IDLE      = 0;
    parameter START_BIT = 1;
    parameter DATA_BITS = 2;
    parameter STOP_BIT  = 3;

    reg [3:0] state, state_next;
    reg q1_RxSerial, q2_RxSerial;
    reg [7:0] RxByte; //LSB First

    reg TimerEna;
    wire TimerInt;
    reg [4:0] BitCount;
    wire [15:0] MaxTimerCount;
    reg db1,db2;
    reg [15:0] TimerCount;

    assign MaxTimerCount = (state == START_BIT) ? TIMER_COUNT_1 : TIMER_COUNT_2;
    assign TimerInt = (TimerCount == MaxTimerCount);
    assign o_RxByte = RxByte;
    
    always @(posedge i_SysClock, negedge i_ResetN) begin
        if (!i_ResetN || !TimerEna) begin
            TimerCount <= 16'd0;
        end
        else begin
            if (TimerCount == MaxTimerCount)
               TimerCount <= 16'd0;
            else
               TimerCount <= TimerCount + 16'd1;
        end
    end

    assign o_RxDone = (state == IDLE) || (state == STOP_BIT);

    always @(posedge i_SysClock, negedge i_ResetN) begin
        if (!i_ResetN) begin
            q1_RxSerial <= 1'b1;
            q2_RxSerial <= 1'b1;
        end
        else begin
            q1_RxSerial <= i_RxSerial; //Meta Stable
            q2_RxSerial <= q1_RxSerial;
        end
    end
    
    always @(posedge i_SysClock, negedge i_ResetN) begin
        if (!i_ResetN) begin
            state <= IDLE;
            db1 <= 0;
            db2 <= 0;
        end
        else begin
            if (state == START_BIT || state == DATA_BITS) begin
                state <= TimerInt ? state_next : state;
                db2 <= TimerInt ? ~db2 : db2;
            end
            else begin
                state <= state_next;
            end
        end
    end

    always @(*) begin
        case (state)
            IDLE: begin
                state_next = (q2_RxSerial == 1'b0) ? START_BIT : IDLE;
            end
            START_BIT: begin
                state_next = DATA_BITS;
            end
            DATA_BITS: begin
                state_next = (BitCount == 4'd8) ? STOP_BIT : DATA_BITS;
            end
            STOP_BIT: begin
                state_next = (q2_RxSerial == 1'b0) ? START_BIT : IDLE;
            end
            default: begin
                state_next = IDLE;
            end
        endcase;
    end
        
    always @(posedge i_SysClock, negedge i_ResetN) begin
        if (!i_ResetN) begin
            BitCount <= 4'd0;
            RxByte <= 8'd0;
            TimerEna <= 1'b0;
        end
        else begin
            if ((state == DATA_BITS) && (state_next == DATA_BITS) && (TimerInt)) begin
                RxByte[7:0] <= {q2_RxSerial,RxByte[7:1]};
                BitCount <= BitCount + 4'd1;
                db1 <= ~db1;
            end
            else if (state == IDLE || state == STOP_BIT) begin
                BitCount <= 4'd0;
                TimerEna <= 1'b0;
            end
            else if (state == START_BIT) begin
                TimerEna <= 1'b1;
            end
        end
    end

endmodule

uart/uart_tx.v
//20210116 UART TX

`timescale 1 ns / 1 ps
`default_nettype none

module uart_tx
    #(
    parameter SYS_CLOCK = 50000000,
    parameter UART_BAUDRATE = 115200
    )(
    input wire i_ResetN,
    input wire i_SysClock,
    input wire i_TxValid,
    input wire [7:0] i_TxByte,
    output wire o_TxSerial,
    output wire o_TxDone
    );

    parameter TIMER_COUNT = (SYS_CLOCK / UART_BAUDRATE);

    parameter IDLE      = 0;
    parameter START_BIT = 1;
    parameter DATA_BITS = 2;
    parameter STOP_BIT  = 3;

    reg [3:0] state, state_next;

    reg TxSerial;
    reg TxValid;
    reg [7:0] TxByte; //LSB First
    reg [2:0] BitCount;

    reg TimerEna;
    wire TimerInt;
    wire [15:0] MaxTimerCount;
    reg [15:0] TimerCount;
    reg db1,db2;

    assign MaxTimerCount = TIMER_COUNT;
    assign TimerInt = (TimerCount == MaxTimerCount);
    
    always @(posedge i_SysClock, negedge i_ResetN) begin
        if (!i_ResetN || !TimerEna) begin
            TimerCount <= 16'd0;
        end
        else begin
            if (TimerCount == MaxTimerCount)
               TimerCount <= 16'd0;
            else
               TimerCount <= TimerCount + 16'd1;
        end
    end

    assign o_TxSerial = TxSerial;
    assign o_TxDone = (state == IDLE) || (state == STOP_BIT);

    always @(posedge i_SysClock, negedge i_ResetN) begin
        if (!i_ResetN) begin
            state <= IDLE;
            db1 <= 0;
            db2 <= 0;
        end
        else begin
            if (state >= START_BIT && state <= STOP_BIT) begin
                state <= TimerInt ? state_next : state;
                db2 <= TimerInt? ~db2 : db2;
            end
            else
                state <= state_next;
        end
    end

    always @(posedge i_SysClock, negedge i_ResetN) begin
        if (!i_ResetN) begin
            TimerEna <= 1'b0;
            BitCount <= 3'd0;
        end
        else begin
            if (state == DATA_BITS) begin
                BitCount <= BitCount + TimerInt;
            end
            else if (state == START_BIT) begin
                TimerEna <= 1'b1;
                BitCount <= 3'd0;
                TxByte <= i_TxByte;
            end
            else if (state == IDLE) begin
                TimerEna <= 1'b0;
            end
        end
    end

    always @(*) begin
        case (state)
            IDLE: begin
                TxSerial = 1'b1;
                state_next = i_TxValid ? START_BIT : IDLE;
            end
            START_BIT: begin
                TxSerial = 1'b0;
                state_next = DATA_BITS;
            end
            DATA_BITS: begin
                TxSerial = TxByte[BitCount];

                if (BitCount == 3'd7)
                    state_next = STOP_BIT;
                else
                    state_next = DATA_BITS;
            end
            STOP_BIT: begin
                TxSerial = 1'b1;
                state_next = i_TxValid ? START_BIT : IDLE;
            end
            default: begin
                TxSerial = 1'b1;
                state_next = IDLE;
            end
        endcase;
    end
    
endmodule

uart/uart_tb.v
//20210116 UART TX/RX Test Bench

`timescale 1 ns / 1 ps
`default_nettype none

module uart_tb;
    parameter SYS_CLOCK = 50000000;
    parameter SYS_PERIOD = (10 ** 9) / SYS_CLOCK;
    parameter UART_BAUDRATE = 115200;

    reg SysClock;
    reg ResetN;
    
    reg TxValid;
    reg [7:0] TxByte;
    wire TxSerial;
    wire TxDone;
    integer Delay;

    reg RxValid;
    wire [7:0] RxByte;
    wire RxSerial;
    wire RxDone;

    assign RxSerial = TxSerial;

    uart_tx
    #(
        SYS_CLOCK,
        UART_BAUDRATE
    )
    uart_tx_inst
    (
        .i_ResetN(ResetN),
        .i_SysClock(SysClock),
        .i_TxValid(TxValid),
        .i_TxByte(TxByte),
        .o_TxSerial(TxSerial),
        .o_TxDone(TxDone)
    );

    uart_rx
    #(
        SYS_CLOCK,
        UART_BAUDRATE
    )
    uart_rx_inst
    (        .i_ResetN(ResetN),
             .i_SysClock(SysClock),
             .i_RxValid(RxValid),
             .o_RxByte(RxByte),
             .i_RxSerial(RxSerial),
             .o_RxDone(RxDone)
    );
    
    initial begin
        $dumpfile("sim.vcd");
        $dumpvars(0,uart_tb);

        #(SYS_PERIOD*10);
        SysClock = 0;
        ResetN = 0;
        TxValid = 0;
        TxByte = 0;
        RxValid = 0;
        #(SYS_PERIOD*10);
        ResetN = 1;
        #(SYS_PERIOD*10);
        
        TxByte = 8'hFF;
        TxValid = 1;
        @(posedge TxDone);
        @(posedge RxDone);
        TxValid = 0;

        TxByte = 8'h00;
        TxValid = 1;
        @(posedge TxDone);
        @(posedge RxDone);
        TxValid = 0;

        TxByte = 8'h55;
        TxValid = 1;
        @(posedge TxDone);
        @(posedge RxDone);
        TxValid = 0;

        TxByte = 8'hAA;
        TxValid = 1;
        @(posedge TxDone);
        @(posedge RxDone);
        TxValid = 0;

        repeat (10) begin
            TxByte = ($random) % 256;
            TxValid = 1;
            @(posedge TxDone);
            @(posedge RxDone);
            TxValid = 0;
            
            if (TxDone != RxDone)
                $display("NG.TxByte:0x%2X,RxByte:0x%2X",TxByte,RxByte);
            else
                $display("OK.TxByte:0x%2X,RxByte:0x%2X",TxByte,RxByte);
        end

        $dumpflush;
        $finish;
    end

    always begin
        #(SYS_PERIOD/2) SysClock = ~SysClock;
    end

endmodule

uart/sim.vcd
$date
	Sat Jan 16 03:12:04 2021
$end
$version
	Icarus Verilog
$end
$timescale
	1ps
$end
$scope module uart_tb $end
$var wire 1 ! RxSerial $end
$var wire 1 " TxSerial $end
$var wire 1 # TxDone $end
$var wire 1 $ RxDone $end
$var wire 8 % RxByte [7:0] $end
$var reg 1 & ResetN $end
$var reg 1 ' RxValid $end
$var reg 1 ( SysClock $end
$var reg 8 ) TxByte [7:0] $end
$var reg 1 * TxValid $end
$scope module uart_rx_inst $end
$var wire 1 & i_ResetN $end
$var wire 1 ! i_RxSerial $end
$var wire 1 ' i_RxValid $end
$var wire 1 ( i_SysClock $end
$var wire 8 + o_RxByte [7:0] $end
$var wire 1 $ o_RxDone $end
$var wire 1 , TimerInt $end
$var wire 16 - MaxTimerCount [15:0] $end
$var reg 5 . BitCount [4:0] $end
$var reg 8 / RxByte [7:0] $end
$var reg 16 0 TimerCount [15:0] $end
$var reg 1 1 TimerEna $end
$var reg 1 2 db1 $end
$var reg 1 3 db2 $end
$var reg 1 4 q1_RxSerial $end
$var reg 1 5 q2_RxSerial $end
$var reg 4 6 state [3:0] $end
$var reg 4 7 state_next [3:0] $end
$upscope $end
$scope module uart_tx_inst $end
$var wire 16 8 MaxTimerCount [15:0] $end
$var wire 1 & i_ResetN $end
$var wire 1 ( i_SysClock $end
$var wire 8 9 i_TxByte [7:0] $end
$var wire 1 * i_TxValid $end
$var wire 1 # o_TxDone $end
$var wire 1 " o_TxSerial $end
$var wire 1 : TimerInt $end
$var reg 3 ; BitCount [2:0] $end
$var reg 16 < TimerCount [15:0] $end
$var reg 1 = TimerEna $end
$var reg 8 > TxByte [7:0] $end
$var reg 1 " TxSerial $end
$var reg 1 ? db1 $end
$var reg 1 @ db2 $end
$var reg 4 A state [3:0] $end
$var reg 4 B state_next [3:0] $end
$upscope $end
$upscope $end
$enddefinitions $end
#0
$dumpvars
bx B
bx A
x@
x?
bx >
x=
bx <
bx ;
x:
bx 9
b110110010 8
bx 7
bx 6
x5
x4
x3
x2
x1
bx 0
bx /
bx .
b0x1xx1x0xx -
x,
bx +
x*
bx )
x(
x'
x&
bx %
x$
x#
x"
x!
$end
#200000
b110110010 -
1#
1$
b0 7
0:
b0 <
0@
0?
b0 A
b0 ;
0=
0,
b0 0
15
14
03
02
b0 6
01
b0 %
b0 +
b0 /
b0 .
b0 B
1!
1"
0'
b0 )
b0 9
0*
0&
1(
#210000
0(
#220000
1(
#230000
0(
#240000
1(
#250000
0(
#260000
1(
#270000
0(
#280000
1(
#290000
0(
#300000
1(
#310000
0(
#320000
1(
#330000
0(
#340000
1(
#350000
0(
#360000
1(
#370000
0(
#380000
1(
#390000
0(
#400000
1(
1&
#410000
0(
#420000
1(
#430000
0(
#440000
1(
#450000
0(
#460000
1(
#470000
0(
#480000
1(
#490000
0(
#500000
1(
#510000
0(
#520000
1(
#530000
0(
#540000
1(
#550000
0(
#560000
1(
#570000
0(
#580000
1(
#590000
0(
#600000
0!
0"
0#
b1 A
b10 B
1(
1*
b11111111 )
b11111111 9
#610000
0(
#620000
04
b11111111 >
1=
1(
#630000
0(
#640000
b1 7
b1 <
05
1(
#650000
0(
#660000
b11011001 -
b10 7
0$
b1 6
b10 <
1(
#670000
0(
#680000
b11 <
11
1(
#690000
0(
#700000
b1 0
b100 <
1(
#710000
0(
#720000
b101 <
b10 0
1(
#730000
0(
#740000
b11 0
b110 <
1(
#750000
0(
#760000
b111 <
b100 0
1(
#770000
0(
#780000
b101 0
b1000 <
1(
#790000
0(
#800000
b1001 <
b110 0
1(
#810000
0(
#820000
b111 0
b1010 <
1(
#830000
0(
#840000
b1011 <
b1000 0
1(
#850000
0(
#860000
b1001 0
b1100 <
1(
#870000
0(
#880000
b1101 <
b1010 0
1(
#890000
0(
#900000
b1011 0
b1110 <
1(
#910000
0(
#920000
b1111 <
b1100 0
1(
#930000
0(
#940000
b1101 0
b10000 <
1(
#950000
0(
#960000
b10001 <
b1110 0
1(
#970000
0(
#980000
b1111 0
b10010 <
1(
#990000
0(
#1000000
b10011 <
b10000 0
1(
#1010000
0(
#1020000
b10001 0
b10100 <
1(
#1030000
0(
#1040000
b10101 <
b10010 0
1(
#1050000
0(
#1060000
b10011 0
b10110 <
1(
#1070000
0(
#1080000
b10111 <
b10100 0
1(
#1090000
0(
#1100000
b10101 0
b11000 <
1(
#1110000
0(
#1120000
b11001 <
b10110 0
1(
#1130000
0(
#1140000
b10111 0
b11010 <
1(
#1150000
0(
#1160000
b11011 <
b11000 0
1(
#1170000
0(
#1180000
b11001 0
b11100 <
1(
#1190000
0(
#1200000
b11101 <
b11010 0
1(
#1210000
0(
#1220000
b11011 0
b11110 <
1(
#1230000
0(
#1240000
b11111 <
b11100 0
1(
#1250000
0(
#1260000
b11101 0
b100000 <
1(
#1270000
0(
#1280000
b100001 <
b11110 0
1(
#1290000
0(
#1300000
b11111 0
b100010 <
1(
#1310000
0(
#1320000
b100011 <
b100000 0
1(
#1330000
0(
#1340000
b100001 0
b100100 <
1(
#1350000
0(
#1360000
b100101 <
b100010 0
1(
#1370000
0(
#1380000
b100011 0
b100110 <
1(
#1390000
0(
#1400000
b100111 <
b100100 0
1(
#1410000
0(
#1420000
b100101 0
b101000 <
1(
#1430000
0(
#1440000
b101001 <
b100110 0
1(
#1450000
0(
#1460000
b100111 0
b101010 <
1(
#1470000
0(
#1480000
b101011 <
b101000 0
1(
#1490000
0(
#1500000
b101001 0
b101100 <
1(
#1510000
0(
#1520000
b101101 <
b101010 0
1(
#1530000
0(
#1540000
b101011 0
b101110 <
1(
#1550000
0(
#1560000
b101111 <
b101100 0
1(
#1570000
0(
#1580000
b101101 0
b110000 <
1(
#1590000
0(
#1600000
b110001 <
b101110 0
1(
#1610000
0(
#1620000
b101111 0
b110010 <
1(
#1630000
0(
#1640000
b110011 <
b110000 0
1(
#1650000
0(
#1660000
b110001 0
b110100 <
1(
#1670000
0(
#1680000
b110101 <
b110010 0
1(
#1690000
0(
#1700000
b110011 0
b110110 <
1(
#1710000
0(
#1720000
b110111 <
b110100 0
1(
#1730000
0(
#1740000
b110101 0
b111000 <
1(
#1750000
0(
#1760000
b111001 <
b110110 0
1(
#1770000
0(
#1780000
b110111 0
b111010 <
1(
#1790000
0(
#1800000
b111011 <
b111000 0
1(
#1810000
0(
#1820000
b111001 0
b111100 <
1(
#1830000
0(
#1840000
b111101 <
b111010 0
1(
#1850000
0(
#1860000
b111011 0
b111110 <
1(
#1870000
0(
#1880000
b111111 <
b111100 0
1(
#1890000
0(
#1900000
b111101 0
b1000000 <
1(
#1910000
0(
#1920000
b1000001 <
b111110 0
1(
#1930000
0(
#1940000
b111111 0
b1000010 <
1(
#1950000
0(
#1960000
b1000011 <
b1000000 0
1(
#1970000
0(
#1980000
b1000001 0
b1000100 <
1(
#1990000
0(
#2000000
b1000101 <
b1000010 0
1(
#2010000
0(
#2020000
b1000011 0
b1000110 <
1(
#2030000
0(
#2040000
b1000111 <
b1000100 0
1(
#2050000
0(
#2060000
b1000101 0
b1001000 <
1(
#2070000
0(
#2080000
b1001001 <
b1000110 0
1(
#2090000
0(
#2100000
b1000111 0
b1001010 <
1(
#2110000
0(
#2120000
b1001011 <
b1001000 0
1(
#2130000
0(
#2140000
b1001001 0
b1001100 <
1(
#2150000
0(
#2160000
b1001101 <
b1001010 0
1(
#2170000
0(
#2180000
b1001011 0
b1001110 <
1(
#2190000
0(
#2200000
b1001111 <
b1001100 0
1(
#2210000
0(
#2220000
b1001101 0
b1010000 <
1(
#2230000
0(
#2240000
b1010001 <
b1001110 0
1(
#2250000
0(
#2260000
b1001111 0
b1010010 <
1(
#2270000
0(
#2280000
b1010011 <
b1010000 0
1(
#2290000
0(
#2300000
b1010001 0
b1010100 <
1(
#2310000
0(
#2320000
b1010101 <
b1010010 0
1(
#2330000
0(
#2340000
b1010011 0
b1010110 <
1(
#2350000
0(
#2360000
b1010111 <
b1010100 0
1(
#2370000
0(
#2380000
b1010101 0
b1011000 <
1(
#2390000
0(
#2400000
b1011001 <
b1010110 0
1(
#2410000
0(
#2420000
b1010111 0
b1011010 <
1(
#2430000
0(
#2440000
b1011011 <
b1011000 0
1(
#2450000
0(
#2460000
b1011001 0
b1011100 <
1(
#2470000
0(
#2480000
b1011101 <
b1011010 0
1(
#2490000
0(
#2500000
b1011011 0
b1011110 <
1(
#2510000
0(
#2520000
b1011111 <
b1011100 0
1(
#2530000
0(
#2540000
b1011101 0
b1100000 <
1(
#2550000
0(
#2560000
b1100001 <
b1011110 0
1(
#2570000
0(
#2580000
b1011111 0
b1100010 <
1(
#2590000
0(
#2600000
b1100011 <
b1100000 0
1(
#2610000
0(
#2620000
b1100001 0
b1100100 <
1(
#2630000
0(
#2640000
b1100101 <
b1100010 0
1(
#2650000
0(
#2660000
b1100011 0
b1100110 <
1(
#2670000
0(
#2680000
b1100111 <
b1100100 0
1(
#2690000
0(
#2700000
b1100101 0
b1101000 <
1(
#2710000
0(
#2720000
b1101001 <
b1100110 0
1(
#2730000
0(
#2740000
b1100111 0
b1101010 <
1(
#2750000
0(
#2760000
b1101011 <
b1101000 0
1(
#2770000
0(
#2780000
b1101001 0
b1101100 <
1(
#2790000
0(
#2800000
b1101101 <
b1101010 0
1(
#2810000
0(
#2820000
b1101011 0
b1101110 <
1(
#2830000
0(
#2840000
b1101111 <
b1101100 0
1(
#2850000
0(
#2860000
b1101101 0
b1110000 <
1(
#2870000
0(
#2880000
b1110001 <
b1101110 0
1(
#2890000
0(
#2900000
b1101111 0
b1110010 <
1(
#2910000
0(
#2920000
b1110011 <
b1110000 0
1(
#2930000
0(
#2940000
b1110001 0
b1110100 <
1(
#2950000
0(
#2960000
b1110101 <
b1110010 0
1(
#2970000
0(
#2980000
b1110011 0
b1110110 <
1(
#2990000
0(
#3000000
b1110111 <
b1110100 0
1(
#3010000
0(
#3020000
b1110101 0
b1111000 <
1(
#3030000
0(
#3040000
b1111001 <
b1110110 0
1(
#3050000
0(
#3060000
b1110111 0
b1111010 <
1(
#3070000
0(
#3080000
b1111011 <
b1111000 0
1(
#3090000
0(
#3100000
b1111001 0
b1111100 <
1(
#3110000
0(
#3120000
b1111101 <
b1111010 0
1(
#3130000
0(
#3140000
b1111011 0
b1111110 <
1(
#3150000
0(
#3160000
b1111111 <
b1111100 0
1(
#3170000
0(
#3180000
b1111101 0
b10000000 <
1(
#3190000
0(
#3200000
b10000001 <
b1111110 0
1(
#3210000
0(
#3220000
b1111111 0
b10000010 <
1(
#3230000
0(
#3240000
b10000011 <
b10000000 0
1(
#3250000
0(
#3260000
b10000001 0
b10000100 <
1(
#3270000
0(
#3280000
b10000101 <
b10000010 0
1(
#3290000
0(
#3300000
b10000011 0
b10000110 <
1(
#3310000
0(
#3320000
b10000111 <
b10000100 0
1(
#3330000
0(
#3340000
b10000101 0
b10001000 <
1(
#3350000
0(
#3360000
b10001001 <
b10000110 0
1(
#3370000
0(
#3380000
b10000111 0
b10001010 <
1(
#3390000
0(
#3400000
b10001011 <
b10001000 0
1(
#3410000
0(
#3420000
b10001001 0
b10001100 <
1(
#3430000
0(
#3440000
b10001101 <
b10001010 0
1(
#3450000
0(
#3460000
b10001011 0
b10001110 <
1(
#3470000
0(
#3480000
b10001111 <
b10001100 0
1(
#3490000
0(
#3500000
b10001101 0
b10010000 <
1(
#3510000
0(
#3520000
b10010001 <
b10001110 0
1(
#3530000
0(
#3540000
b10001111 0
b10010010 <
1(
#3550000
0(
#3560000
b10010011 <
b10010000 0
1(
#3570000
0(
#3580000
b10010001 0
b10010100 <
1(
#3590000
0(
#3600000
b10010101 <
b10010010 0
1(
#3610000
0(
#3620000
b10010011 0
b10010110 <
1(
#3630000
0(
#3640000
b10010111 <
b10010100 0
1(
#3650000
0(
#3660000
b10010101 0
b10011000 <
1(
#3670000
0(
#3680000
b10011001 <
b10010110 0
1(
#3690000
0(
#3700000
b10010111 0
b10011010 <
1(
#3710000
0(
#3720000
b10011011 <
b10011000 0
1(
#3730000
0(
#3740000
b10011001 0
b10011100 <
1(
#3750000
0(
#3760000
b10011101 <
b10011010 0
1(
#3770000
0(
#3780000
b10011011 0
b10011110 <
1(
#3790000
0(
#3800000
b10011111 <
b10011100 0
1(
#3810000
0(
#3820000
b10011101 0
b10100000 <
1(
#3830000
0(
#3840000
b10100001 <
b10011110 0
1(
#3850000
0(
#3860000
b10011111 0
b10100010 <
1(
#3870000
0(
#3880000
b10100011 <
b10100000 0
1(
#3890000
0(
#3900000
b10100001 0
b10100100 <
1(
#3910000
0(
#3920000
b10100101 <
b10100010 0
1(
#3930000
0(
#3940000
b10100011 0
b10100110 <
1(
#3950000
0(
#3960000
b10100111 <
b10100100 0
1(
#3970000
0(
#3980000
b10100101 0
b10101000 <
1(
#3990000
0(
#4000000
b10101001 <
b10100110 0
1(
#4010000
0(
#4020000
b10100111 0
b10101010 <
1(
#4030000
0(
#4040000
b10101011 <
b10101000 0
1(
#4050000
0(
#4060000
b10101001 0
b10101100 <
1(
#4070000
0(
#4080000
b10101101 <
b10101010 0
1(
#4090000
0(
#4100000
b10101011 0
b10101110 <
1(
#4110000
0(
#4120000
b10101111 <
b10101100 0
1(
#4130000
0(
#4140000
b10101101 0
b10110000 <
1(
#4150000
0(
#4160000
b10110001 <
b10101110 0
1(
#4170000
0(
#4180000
b10101111 0
b10110010 <
1(
#4190000
0(
#4200000
b10110011 <
b10110000 0
1(
#4210000
0(
#4220000
b10110001 0
b10110100 <
1(
#4230000
0(
#4240000
b10110101 <
b10110010 0
1(
#4250000
0(
#4260000
b10110011 0
b10110110 <
1(
#4270000
0(
#4280000
b10110111 <
b10110100 0
1(
#4290000
0(
#4300000
b10110101 0
b10111000 <
1(
#4310000
0(
#4320000
b10111001 <
b10110110 0
1(
#4330000
0(
#4340000
b10110111 0
b10111010 <
1(
#4350000
0(
#4360000
b10111011 <
b10111000 0
1(
#4370000
0(
#4380000
b10111001 0
b10111100 <
1(
#4390000
0(
#4400000
b10111101 <
b10111010 0
1(
#4410000
0(
#4420000
b10111011 0
b10111110 <
1(
#4430000
0(
#4440000
b10111111 <
b10111100 0
1(
#4450000
0(
#4460000
b10111101 0
b11000000 <
1(
#4470000
0(
#4480000
b11000001 <
b10111110 0
1(
#4490000
0(
#4500000
b10111111 0
b11000010 <
1(
#4510000
0(
#4520000
b11000011 <
b11000000 0
1(
#4530000
0(
#4540000
b11000001 0
b11000100 <
1(
#4550000
0(
#4560000
b11000101 <
b11000010 0
1(
#4570000
0(
#4580000
b11000011 0
b11000110 <
1(
#4590000
0(
#4600000
b11000111 <
b11000100 0
1(
#4610000
0(
#4620000
b11000101 0
b11001000 <
1(
#4630000
0(
#4640000
b11001001 <
b11000110 0
1(
#4650000
0(
#4660000
b11000111 0
b11001010 <
1(
#4670000
0(
#4680000
b11001011 <
b11001000 0
1(
#4690000
0(
#4700000
b11001001 0
b11001100 <
1(
#4710000
0(
#4720000
b11001101 <
b11001010 0
1(
#4730000
0(
#4740000
b11001011 0
b11001110 <
1(
#4750000
0(
#4760000
b11001111 <
b11001100 0
1(
#4770000
0(
#4780000
b11001101 0
b11010000 <
1(
#4790000
0(
#4800000
b11010001 <
b11001110 0
1(
#4810000
0(
#4820000
b11001111 0
b11010010 <
1(
#4830000
0(
#4840000
b11010011 <
b11010000 0
1(
#4850000
0(
#4860000
b11010001 0
b11010100 <
1(
#4870000
0(
#4880000
b11010101 <
b11010010 0
1(
#4890000
0(
#4900000
b11010011 0
b11010110 <
1(
#4910000
0(
#4920000
b11010111 <
b11010100 0
1(
#4930000
0(
#4940000
b11010101 0
b11011000 <
1(
#4950000
0(
#4960000
b11011001 <
b11010110 0
1(
#4970000
0(
#4980000
b11010111 0
b11011010 <
1(
#4990000
0(
#5000000
b11011011 <
b11011000 0
1(
#5010000
0(
#5020000
1,
b11011001 0
b11011100 <
1(
#5030000
0(
#5040000
b110110010 -
b11011101 <
0,
b0 0
13
b10 6
1(
#5050000
0(
#5060000
b1 0
b11011110 <
1(
#5070000
0(
#5080000
b11011111 <
b10 0
1(
#5090000
0(
#5100000
b11 0
b11100000 <
1(
#5110000
0(
#5120000
b11100001 <
b100 0
1(
#5130000
0(
#5140000
b101 0
b11100010 <
1(
#5150000
0(
#5160000
b11100011 <
b110 0
1(
#5170000
0(
#5180000
b111 0
b11100100 <
1(
#5190000
0(
#5200000
b11100101 <
b1000 0
1(
#5210000
0(
#5220000
b1001 0
b11100110 <
1(
#5230000
0(
#5240000
b11100111 <
b1010 0
1(
#5250000
0(
#5260000
b1011 0
b11101000 <
1(
#5270000
0(
#5280000
b11101001 <
b1100 0
1(
#5290000
0(
#5300000
b1101 0
b11101010 <
1(
#5310000
0(
#5320000
b11101011 <
b1110 0
1(
#5330000
0(
#5340000
b1111 0
b11101100 <
1(
#5350000
0(
#5360000
b11101101 <
b10000 0
1(
#5370000
0(
#5380000
b10001 0
b11101110 <
1(
#5390000
0(
#5400000
b11101111 <
b10010 0
1(
#5410000
0(
#5420000
b10011 0
b11110000 <
1(
#5430000
0(
#5440000
b11110001 <
b10100 0
1(
#5450000
0(
#5460000
b10101 0
b11110010 <
1(
#5470000
0(
#5480000
b11110011 <
b10110 0
1(
#5490000
0(
#5500000
b10111 0
b11110100 <
1(
#5510000
0(
#5520000
b11110101 <
b11000 0
1(
#5530000
0(
#5540000
b11001 0
b11110110 <
1(
#5550000
0(
#5560000
b11110111 <
b11010 0
1(
#5570000
0(
#5580000
b11011 0
b11111000 <
1(
#5590000
0(
#5600000
b11111001 <
b11100 0
1(
#5610000
0(
#5620000
b11101 0
b11111010 <
1(
#5630000
0(
#5640000
b11111011 <
b11110 0
1(
#5650000
0(
#5660000
b11111 0
b11111100 <
1(
#5670000
0(
#5680000
b11111101 <
b100000 0
1(
#5690000
0(
#5700000
b100001 0
b11111110 <
1(
#5710000
0(
#5720000
b11111111 <
b100010 0
1(
#5730000
0(
#5740000
b100011 0
b100000000 <
1(
#5750000
0(
#5760000
b100000001 <
b100100 0
1(
#5770000
0(
#5780000
b100101 0
b100000010 <
1(
#5790000
0(
#5800000
b100000011 <
b100110 0
1(
#5810000
0(
#5820000
b100111 0
b100000100 <
1(
#5830000
0(
#5840000
b100000101 <
b101000 0
1(
#5850000
0(
#5860000
b101001 0
b100000110 <
1(
#5870000
0(
#5880000
b100000111 <
b101010 0
1(
#5890000
0(
#5900000
b101011 0
b100001000 <
1(
#5910000
0(
#5920000
b100001001 <
b101100 0
1(
#5930000
0(
#5940000
b101101 0
b100001010 <
1(
#5950000
0(
#5960000
b100001011 <
b101110 0
1(
#5970000
0(
#5980000
b101111 0
b100001100 <
1(
#5990000
0(
#6000000
b100001101 <
b110000 0
1(
#6010000
0(
#6020000
b110001 0
b100001110 <
1(
#6030000
0(
#6040000
b100001111 <
b110010 0
1(
#6050000
0(
#6060000
b110011 0
b100010000 <
1(
#6070000
0(
#6080000
b100010001 <
b110100 0
1(
#6090000
0(
#6100000
b110101 0
b100010010 <
1(
#6110000
0(
#6120000
b100010011 <
b110110 0
1(
#6130000
0(
#6140000
b110111 0
b100010100 <
1(
#6150000
0(
#6160000
b100010101 <
b111000 0
1(
#6170000
0(
#6180000
b111001 0
b100010110 <
1(
#6190000
0(
#6200000
b100010111 <
b111010 0
1(
#6210000
0(
#6220000
b111011 0
b100011000 <
1(
#6230000
0(
#6240000
b100011001 <
b111100 0
1(
#6250000
0(
#6260000
b111101 0
b100011010 <
1(
#6270000
0(
#6280000
b100011011 <
b111110 0
1(
#6290000
0(
#6300000
b111111 0
b100011100 <
1(
#6310000
0(
#6320000
b100011101 <
b1000000 0
1(
#6330000
0(
#6340000
b1000001 0
b100011110 <
1(
#6350000
0(
#6360000
b100011111 <
b1000010 0
1(
#6370000
0(
#6380000
b1000011 0
b100100000 <
1(
#6390000
0(
#6400000
b100100001 <
b1000100 0
1(
#6410000
0(
#6420000
b1000101 0
b100100010 <
1(
#6430000
0(
#6440000
b100100011 <
b1000110 0
1(
#6450000
0(
#6460000
b1000111 0
b100100100 <
1(
#6470000
0(
#6480000
b100100101 <
b1001000 0
1(
#6490000
0(
#6500000
b1001001 0
b100100110 <
1(
#6510000
0(
#6520000
b100100111 <
b1001010 0
1(
#6530000
0(
#6540000
b1001011 0
b100101000 <
1(
#6550000
0(
#6560000
b100101001 <
b1001100 0
1(
#6570000
0(
#6580000
b1001101 0
b100101010 <
1(
#6590000
0(
#6600000
b100101011 <
b1001110 0
1(
#6610000
0(
#6620000
b1001111 0
b100101100 <
1(
#6630000
0(
#6640000
b100101101 <
b1010000 0
1(
#6650000
0(
#6660000
b1010001 0
b100101110 <
1(
#6670000
0(
#6680000
b100101111 <
b1010010 0
1(
#6690000
0(
#6700000
b1010011 0
b100110000 <
1(
#6710000
0(
#6720000
b100110001 <
b1010100 0
1(
#6730000
0(
#6740000
b1010101 0
b100110010 <
1(
#6750000
0(
#6760000
b100110011 <
b1010110 0
1(
#6770000
0(
#6780000
b1010111 0
b100110100 <
1(
#6790000
0(
#6800000
b100110101 <
b1011000 0
1(
#6810000
0(
#6820000
b1011001 0
b100110110 <
1(
#6830000
0(
#6840000
b100110111 <
b1011010 0
1(
#6850000
0(
#6860000
b1011011 0
b100111000 <
1(
#6870000
0(
#6880000
b100111001 <
b1011100 0
1(
#6890000
0(
#6900000
b1011101 0
b100111010 <
1(
#6910000
0(
#6920000
b100111011 <
b1011110 0
1(
#6930000
0(
#6940000
b1011111 0
b100111100 <
1(
#6950000
0(
#6960000
b100111101 <
b1100000 0
1(
#6970000
0(
#6980000
b1100001 0
b100111110 <
1(
#6990000
0(
#7000000
b100111111 <
b1100010 0
1(
#7010000
0(
#7020000
b1100011 0
b101000000 <
1(
#7030000
0(
