uart2/rtl/uart_rx.v
//20210126 UART Receiver 

`timescale 1 ns / 1 ps
`default_nettype none
`define MAX_BITCNT 9

`define ASSERT(signal, value) \
    if (signal !== value) begin \
        $display("ASSERTION FAILED in %m: signal != value"); \
        $finish; \
    end

module uart_rx_control_unit
    (
    input wire i_ResetN,
    input wire i_SysClock,
    input wire [3:0] i_bit_cnt,
    output wire o_RxDone,
    output reg o_Start,
    input wire i_RxSerial,
    output wire o_synRxSerial
    );

    parameter s_IDLE  = 1'b0;
    parameter s_RCVRS = 1'b1;

    reg state, state_next;
    reg q1_RxSerial, q2_RxSerial;

    assign o_synRxSerial = q2_RxSerial;
    assign o_RxDone = (state == s_IDLE) ? 1 : 0;

    always @(posedge i_SysClock, negedge i_ResetN) begin : SyncRxSerial
        if (!i_ResetN) begin
            q1_RxSerial <= 1;
            q2_RxSerial <= 1;
        end else begin
            q1_RxSerial <= i_RxSerial; //Meta Stable
            q2_RxSerial <= q1_RxSerial;
        end
    end

    always @(posedge i_SysClock) begin : UpdateStateMachine
        if (!i_ResetN) begin
            state <= s_IDLE;
        end else begin
            state <= state_next;
        end
    end

    always @(*) begin : NextStateMachine
        o_Start = 0;
        state_next = s_IDLE;
        
        case (state)
            s_IDLE: begin  
                if (q2_RxSerial == 0) begin
                    o_Start = 1;
                    state_next = s_RCVRS;
                end
            end
            s_RCVRS: begin //b0,1,2,3,4,5,6,7,stop_bit
                if (i_bit_cnt != (`MAX_BITCNT + 1))
                    state_next = s_RCVRS;
            end
            default: begin
                state_next = s_IDLE;
            end
        endcase
    end

endmodule

module uart_rx_datapath_unit
    #(
    parameter SYS_CLOCK = 50000000,
    parameter UART_BAUDRATE = 115200
    )(
    input wire i_ResetN,
    input wire i_SysClock,
    output reg [7:0] o_RxByte,
    input wire i_Start,
    output reg [3:0] o_bit_cnt,
    input wire i_RxSerial
    );

    localparam MAX_CYCLE_CNT_HALF = ((SYS_CLOCK * 10 / UART_BAUDRATE / 2 + 5)) / 10 - 1;
    localparam MAX_CYCLE_CNT = ((SYS_CLOCK * 10 / UART_BAUDRATE + 5)) / 10  - 1;

    reg [7:0] shift_reg;
    reg handing;
    reg [$clog2(MAX_CYCLE_CNT):0] cycle_cnt;

    wire baudrate_half_period_cond;
    wire baudrate_period_cond;
    //reg detStopErr;

    assign baudrate_half_period_cond = (cycle_cnt == MAX_CYCLE_CNT_HALF) && (o_bit_cnt == 0) ? 1 : 0;
    assign baudrate_period_cond = (cycle_cnt == MAX_CYCLE_CNT) && (o_bit_cnt != 0) ? 1 : 0;

    always @(posedge i_SysClock) begin : BaudRateGen
        if (!i_ResetN) begin
            cycle_cnt <= 0;
        end else begin
            if (baudrate_half_period_cond == 1 || baudrate_period_cond == 1 || handing == 0) begin
                cycle_cnt <= 0;
            end else begin
                cycle_cnt <= cycle_cnt + 1;
            end 
        end
    end

    always @(posedge i_SysClock) begin : SerialIn
        if (!i_ResetN) begin
            o_bit_cnt <= 0;
            shift_reg <= 0;
            handing <= 0;
            //detStopErr <= 0;
            o_RxByte <= 0;
        end else begin
            if (i_Start) begin
                o_bit_cnt <= 0;
                handing <= 1;
            end else if (baudrate_half_period_cond == 1) begin
                o_bit_cnt <= o_bit_cnt + 1;
            end else if (baudrate_period_cond == 1) begin
                shift_reg <= {i_RxSerial,shift_reg[7:1]};
                o_bit_cnt <= o_bit_cnt + 1;

                if (o_bit_cnt == `MAX_BITCNT) begin
                    handing <= 0;
                    //detStopErr <= !i_RxSerial;
                    o_RxByte <= shift_reg;
                end
            end 
        end
    end

endmodule

module uart_rx
    #(
    parameter SYS_CLOCK = 50000000,
    parameter UART_BAUDRATE = 115200
    )(
    input wire i_ResetN,
    input wire i_SysClock,
    output wire [7:0] o_RxByte,
    input wire i_RxSerial,
    output wire o_RxDone
    );

    wire Start;
    wire synRxSerial;
    wire [3:0] bit_cnt;
    
    uart_rx_control_unit
    ctl_inst
    (
        .i_ResetN(i_ResetN),
        .i_SysClock(i_SysClock),
        .i_bit_cnt(bit_cnt),
        .o_RxDone(o_RxDone),
        .o_Start(Start),
        .i_RxSerial(i_RxSerial),
        .o_synRxSerial(synRxSerial)
    );

    uart_rx_datapath_unit
    #(
        SYS_CLOCK,
        UART_BAUDRATE
    )
    dp_inst
    (
        .i_ResetN(i_ResetN),
        .i_SysClock(i_SysClock),
        .o_RxByte(o_RxByte),
        .i_Start(Start),
        .o_bit_cnt(bit_cnt),
        .i_RxSerial(synRxSerial)
    );

endmodule
`resetall

uart2/rtl/uart_tx.v
//20210126 UART Transmitter

`timescale 1 ns / 1 ps
`default_nettype none
`define MAX_BITCNT 9

`define ASSERT(signal, value) \
    if (signal !== value) begin \
        $display("ASSERTION FAILED in %m: signal != value"); \
        $finish; \
    end

module uart_tx_control_unit
    (
    input wire i_ResetN,
    input wire i_SysClock,
    input wire i_TxValid,
    input wire [3:0] i_bit_cnt,
    output wire o_TxDone,
    output reg o_Start,
    output reg o_Shift
    );

    parameter s_IDLE  = 1'b0;
    parameter s_TRANS = 1'b1;

    assign o_TxDone = (state == s_IDLE) ? 1 : 0;

    reg state, state_next;

    always @(posedge i_SysClock) begin : UpdateStateMachine
        if (!i_ResetN) begin
            state <= s_IDLE;
        end else begin
            state <= state_next;
        end
    end

    always @(*) begin : NextStateMachine
        o_Start = 0;
        o_Shift = 0;
        state_next = s_IDLE;
        
        case (state)
            s_IDLE: begin
                if (i_TxValid) begin
                    o_Start = 1;
                    state_next = s_TRANS;
                end
            end
            s_TRANS: begin //b0,1,2,3,4,5,6,7,stop_bit
                if (i_bit_cnt != (`MAX_BITCNT + 1))
                    state_next = s_TRANS;

                if (i_bit_cnt >= 1 && i_bit_cnt <= (`MAX_BITCNT-1))
                    o_Shift = 1;
            end
            default: begin
                state_next = s_IDLE;
            end
        endcase
    end

endmodule

module uart_tx_datapath_unit
    #(
    parameter SYS_CLOCK = 50000000,
    parameter UART_BAUDRATE = 115200
    )(
    input wire i_ResetN,
    input wire i_SysClock,
    input wire [7:0] i_TxByte,
    input wire i_Shift,
    input wire i_Start,
    output reg [3:0] o_bit_cnt,
    output wire o_TxSerial
    );

    localparam MAX_CYCLE_CNT = ((SYS_CLOCK * 10 / UART_BAUDRATE + 5) / 10) - 1;

    reg [7:0] TxByte;
    reg [8:0] shift_reg;
    reg handing;
    reg [$clog2(MAX_CYCLE_CNT):0] cycle_cnt;
    wire baudrate_period_cond;

    assign o_TxSerial = shift_reg[0];
    assign baudrate_period_cond = (cycle_cnt == MAX_CYCLE_CNT) ? 1 : 0;
    
    always @(posedge i_SysClock) begin : BaudRateGen
        if (!i_ResetN) begin
            cycle_cnt <= 0;
        end else begin
            if (baudrate_period_cond == 1 || handing == 0) begin
                cycle_cnt <= 0;
            end else begin
                cycle_cnt <= cycle_cnt + 1;
            end 
        end
    end
    
    always @(posedge i_SysClock) begin : SerialOut
        if (!i_ResetN) begin
            o_bit_cnt <= 0;
            shift_reg <= {9{1'b1}};
            TxByte <= 0;
            handing <= 0;
        end else begin
            if (i_Start) begin
                o_bit_cnt <= 0;
                shift_reg[0] <= 0;
                TxByte <= i_TxByte;
                handing <= 1;
            end if (baudrate_period_cond == 1) begin
                if (handing == 1) begin
                    shift_reg <= (i_Shift == 1) ? {shift_reg[0],shift_reg[8:1]} : {1'b1,TxByte};
                    o_bit_cnt <= o_bit_cnt + 1;
                end
                
                if (o_bit_cnt == `MAX_BITCNT)
                    handing = 0;
            end 
        end
    end

endmodule

module uart_tx
    #(
    parameter SYS_CLOCK = 50000000,
    parameter UART_BAUDRATE = 115200
    )(
    input wire i_ResetN,
    input wire i_SysClock,
    input wire i_TxValid,
    input wire [7:0] i_TxByte,
    output wire o_TxSerial,
    output wire o_TxDone
    );

    wire Start;
    wire Shift;
    wire [3:0] bit_cnt;
    
    uart_tx_control_unit
    ctl_inst
    (
        .i_ResetN(i_ResetN),
        .i_SysClock(i_SysClock),
        .i_TxValid(i_TxValid),
        .i_bit_cnt(bit_cnt),
        .o_TxDone(o_TxDone),
        .o_Start(Start),
        .o_Shift(Shift)
    );

    uart_tx_datapath_unit
    #(
        SYS_CLOCK,
        UART_BAUDRATE
    )
    dp_inst
    (
        .i_ResetN(i_ResetN),
        .i_SysClock(i_SysClock),
        .i_TxByte(i_TxByte),
        .i_Start(Start),
        .i_Shift(Shift),
        .o_bit_cnt(bit_cnt),
        .o_TxSerial(o_TxSerial)
    );

endmodule
`resetall

uart2/sim/uart_tb.v
//20210126 UART Transmitter/Receiver Test Bench

`timescale 1 ns / 1 ps
`default_nettype none

`define ASSERT(signal, value) \
        if (signal !== value) begin \
            $display("ASSERTION FAILED in %m: signal != value"); \
            $finish; \
        end

module uart_tb;
    parameter SYS_CLOCK = 50000000;
    parameter SYS_PERIOD = (10 ** 9) / SYS_CLOCK;
    parameter UART_BAUDRATE = SYS_CLOCK / 8;//115200;

    reg SysClock;
    reg ResetN;
    
    reg TxValid;
    reg [7:0] TxByte;
    wire TxSerial;
    wire TxDone;
    reg toggle;

    wire [7:0] RxByte;
    wire RxSerial;
    wire RxDone;

    assign RxSerial = TxSerial;
     
    uart_tx
    #(
        SYS_CLOCK,
        UART_BAUDRATE
    )
    uart_tx_inst
    (
        .i_ResetN(ResetN),
        .i_SysClock(SysClock),
        .i_TxValid(TxValid),
        .i_TxByte(TxByte),
        .o_TxSerial(TxSerial),
        .o_TxDone(TxDone)
    );

    uart_rx
    #(
        SYS_CLOCK,
        UART_BAUDRATE
    )
    uart_rx_inst
    (
        .i_ResetN(ResetN),
        .i_SysClock(SysClock),
        .o_RxByte(RxByte),
        .i_RxSerial(RxSerial),
        .o_RxDone(RxDone)
    );
    
    initial begin
        $dumpfile("sim.vcd");
        $dumpvars(0,uart_tb);

        #(SYS_PERIOD*10);
        SysClock = 0;
        ResetN = 0;
        TxValid = 0;
        TxByte = 0;
        toggle = 0;
        
        repeat (10) begin
            #(SYS_PERIOD*1)
            @(negedge SysClock)
            ResetN = 1;
            #(SYS_PERIOD*10);
            @(negedge SysClock)
            
            TxByte = 8'h55;       
            //TxByte = $random / 256;        

            @(negedge SysClock)
            TxValid = 1;
            @(negedge SysClock)
            TxValid = 0;
            
            while (!TxDone) begin #1; end
            
            while (!RxDone) begin #1; end
            
            toggle = ~toggle;        
            
            if (TxByte == RxByte)
                $display("OK.TxByte:0x%2X,RxByte:0x%2X",TxByte,RxByte);
            else
                $display("NG.TxByte:0x%2X,RxByte:0x%2X",TxByte,RxByte);
        end

        #(SYS_PERIOD*100);

        $dumpflush;
        $finish;
    end

    always begin
        #(SYS_PERIOD/2) SysClock = ~SysClock;
    end

endmodule
`resetall

uart2/sim/sim.vcd
$date
	Tue Jan 26 18:33:13 2021
$end
$version
	Icarus Verilog
$end
$timescale
	1ps
$end
$scope module uart_tb $end
$var wire 1 ! RxSerial $end
$var wire 1 " TxSerial $end
$var wire 1 # TxDone $end
$var wire 1 $ RxDone $end
$var wire 8 % RxByte [7:0] $end
$var reg 1 & ResetN $end
$var reg 1 ' SysClock $end
$var reg 8 ( TxByte [7:0] $end
$var reg 1 ) TxValid $end
$var reg 1 * toggle $end
$scope module uart_rx_inst $end
$var wire 1 & i_ResetN $end
$var wire 1 ! i_RxSerial $end
$var wire 1 ' i_SysClock $end
$var wire 1 + synRxSerial $end
$var wire 1 $ o_RxDone $end
$var wire 8 , o_RxByte [7:0] $end
$var wire 4 - bit_cnt [3:0] $end
$var wire 1 . Start $end
$scope module ctl_inst $end
$var wire 1 & i_ResetN $end
$var wire 1 ! i_RxSerial $end
$var wire 1 ' i_SysClock $end
$var wire 1 + o_synRxSerial $end
$var wire 1 $ o_RxDone $end
$var wire 4 / i_bit_cnt [3:0] $end
$var reg 1 . o_Start $end
$var reg 1 0 q1_RxSerial $end
$var reg 1 1 q2_RxSerial $end
$var reg 1 2 state $end
$var reg 1 3 state_next $end
$scope begin NextStateMachine $end
$upscope $end
$scope begin SyncRxSerial $end
$upscope $end
$scope begin UpdateStateMachine $end
$upscope $end
$upscope $end
$scope module dp_inst $end
$var wire 1 & i_ResetN $end
$var wire 1 + i_RxSerial $end
$var wire 1 . i_Start $end
$var wire 1 ' i_SysClock $end
$var wire 1 4 baudrate_period_cond $end
$var wire 1 5 baudrate_half_period_cond $end
$var reg 4 6 cycle_cnt [3:0] $end
$var reg 1 7 handing $end
$var reg 8 8 o_RxByte [7:0] $end
$var reg 4 9 o_bit_cnt [3:0] $end
$var reg 8 : shift_reg [7:0] $end
$scope begin BaudRateGen $end
$upscope $end
$scope begin SerialIn $end
$upscope $end
$upscope $end
$upscope $end
$scope module uart_tx_inst $end
$var wire 1 & i_ResetN $end
$var wire 1 ' i_SysClock $end
$var wire 8 ; i_TxByte [7:0] $end
$var wire 1 ) i_TxValid $end
$var wire 1 " o_TxSerial $end
$var wire 1 # o_TxDone $end
$var wire 4 < bit_cnt [3:0] $end
$var wire 1 = Start $end
$var wire 1 > Shift $end
$scope module ctl_inst $end
$var wire 1 & i_ResetN $end
$var wire 1 ' i_SysClock $end
$var wire 1 ) i_TxValid $end
$var wire 1 # o_TxDone $end
$var wire 4 ? i_bit_cnt [3:0] $end
$var reg 1 > o_Shift $end
$var reg 1 = o_Start $end
$var reg 1 @ state $end
$var reg 1 A state_next $end
$scope begin NextStateMachine $end
$upscope $end
$scope begin UpdateStateMachine $end
$upscope $end
$upscope $end
$scope module dp_inst $end
$var wire 1 & i_ResetN $end
$var wire 1 > i_Shift $end
$var wire 1 = i_Start $end
$var wire 1 ' i_SysClock $end
$var wire 8 B i_TxByte [7:0] $end
$var wire 1 " o_TxSerial $end
$var wire 1 C baudrate_period_cond $end
$var reg 8 D TxByte [7:0] $end
$var reg 4 E cycle_cnt [3:0] $end
$var reg 1 F handing $end
$var reg 4 G o_bit_cnt [3:0] $end
$var reg 9 H shift_reg [8:0] $end
$scope begin BaudRateGen $end
$upscope $end
$scope begin SerialOut $end
$upscope $end
$upscope $end
$upscope $end
$upscope $end
$enddefinitions $end
#0
$dumpvars
bx H
bx G
xF
bx E
bx D
xC
bx B
xA
x@
bx ?
x>
x=
bx <
bx ;
bx :
bx 9
bx 8
x7
bx 6
x5
x4
x3
x2
x1
x0
bx /
x.
bx -
bx ,
x+
x*
x)
bx (
x'
x&
bx %
x$
x#
x"
x!
$end
#200000
05
04
1$
1#
0C
1!
1"
03
0.
b0 %
b0 ,
b0 8
07
b0 :
b0 -
b0 /
b0 9
b0 6
02
0F
b0 D
b111111111 H
b0 <
b0 ?
b0 G
b0 E
0@
1+
11
10
0A
0>
0=
0*
b0 (
b0 ;
b0 B
0)
0&
1'
#210000
0'
#220000
1'
#230000
1&
0'
#240000
1'
#250000
0'
#260000
1'
#270000
0'
#280000
1'
#290000
0'
#300000
1'
#310000
0'
#320000
1'
#330000
0'
#340000
1'
#350000
0'
#360000
1'
#370000
0'
#380000
1'
#390000
0'
#400000
1'
#410000
0'
#420000
1'
#430000
b1010101 (
b1010101 ;
b1010101 B
0'
#440000
1'
#450000
1A
1=
1)
0'
#460000
0#
0!
0"
1A
0=
1F
b1010101 D
b111111110 H
1@
1'
#470000
1A
0)
0'
#480000
b1 E
00
1'
#490000
0'
#500000
13
1.
b10 E
0+
01
1'
#510000
0'
#520000
0$
13
0.
17
12
b11 E
1'
#530000
0'
#540000
b1 6
b100 E
1'
#550000
0'
#560000
b10 6
b101 E
1'
#570000
0'
#580000
15
b11 6
b110 E
1'
#590000
0'
#600000
05
1C
13
b1 -
b1 /
b1 9
b0 6
b111 E
1'
#610000
0'
#620000
0C
1>
1A
1!
1"
b1 6
b1 <
b1 ?
b1 G
b101010101 H
b0 E
1'
#630000
0'
#640000
b10 6
b1 E
10
1'
#650000
0'
#660000
13
b11 6
b10 E
1+
11
1'
#670000
0'
#680000
b100 6
b11 E
1'
#690000
0'
#700000
b101 6
b100 E
1'
#710000
0'
#720000
b110 6
b101 E
1'
#730000
0'
#740000
14
b111 6
b110 E
1'
#750000
0'
#760000
04
1C
13
b10 -
b10 /
b10 9
b10000000 :
b0 6
b111 E
1'
#770000
0'
#780000
0C
1A
1>
0!
0"
b1 6
b10 <
b10 ?
b10 G
b110101010 H
b0 E
1'
#790000
0'
#800000
b10 6
b1 E
00
1'
#810000
0'
#820000
13
b11 6
b10 E
0+
01
1'
#830000
0'
#840000
b100 6
b11 E
1'
#850000
0'
#860000
b101 6
b100 E
1'
#870000
0'
#880000
b110 6
b101 E
1'
#890000
0'
#900000
14
b111 6
b110 E
1'
#910000
0'
#920000
04
1C
13
b11 -
b11 /
b11 9
b1000000 :
b0 6
b111 E
1'
#930000
0'
#940000
0C
1A
1>
1!
1"
b1 6
b11 <
b11 ?
b11 G
b11010101 H
b0 E
1'
#950000
0'
#960000
b10 6
b1 E
10
1'
#970000
0'
#980000
13
b11 6
b10 E
1+
11
1'
#990000
0'
#1000000
b100 6
b11 E
1'
#1010000
0'
#1020000
b101 6
b100 E
1'
#1030000
0'
#1040000
b110 6
b101 E
1'
#1050000
0'
#1060000
14
b111 6
b110 E
1'
#1070000
0'
#1080000
04
1C
13
b100 -
b100 /
b100 9
b10100000 :
b0 6
b111 E
1'
#1090000
0'
#1100000
0C
1A
1>
0!
0"
b1 6
b100 <
b100 ?
b100 G
b101101010 H
b0 E
1'
#1110000
0'
#1120000
b10 6
b1 E
00
1'
#1130000
0'
#1140000
13
b11 6
b10 E
0+
01
1'
#1150000
0'
#1160000
b100 6
b11 E
1'
#1170000
0'
#1180000
b101 6
b100 E
1'
#1190000
0'
#1200000
b110 6
b101 E
1'
#1210000
0'
#1220000
14
b111 6
b110 E
1'
#1230000
0'
#1240000
04
1C
13
b101 -
b101 /
b101 9
b1010000 :
b0 6
b111 E
1'
#1250000
0'
#1260000
0C
1A
1>
1!
1"
b1 6
b101 <
b101 ?
b101 G
b10110101 H
b0 E
1'
#1270000
0'
#1280000
b10 6
b1 E
10
1'
#1290000
0'
#1300000
13
b11 6
b10 E
1+
11
1'
#1310000
0'
#1320000
b100 6
b11 E
1'
#1330000
0'
#1340000
b101 6
b100 E
1'
#1350000
0'
#1360000
b110 6
b101 E
1'
#1370000
0'
#1380000
14
b111 6
b110 E
1'
#1390000
0'
#1400000
04
1C
13
b110 -
b110 /
b110 9
b10101000 :
b0 6
b111 E
1'
#1410000
0'
#1420000
0C
1A
1>
0!
0"
b1 6
b110 <
b110 ?
b110 G
b101011010 H
b0 E
1'
#1430000
0'
#1440000
b10 6
b1 E
00
1'
#1450000
0'
#1460000
13
b11 6
b10 E
0+
01
1'
#1470000
0'
#1480000
b100 6
b11 E
1'
#1490000
0'
#1500000
b101 6
b100 E
1'
#1510000
0'
#1520000
b110 6
b101 E
1'
#1530000
0'
#1540000
14
b111 6
b110 E
1'
#1550000
0'
#1560000
04
1C
13
b111 -
b111 /
b111 9
b1010100 :
b0 6
b111 E
1'
#1570000
0'
#1580000
0C
1A
1>
1!
1"
b1 6
b111 <
b111 ?
b111 G
b10101101 H
b0 E
1'
#1590000
0'
#1600000
b10 6
b1 E
10
1'
#1610000
0'
#1620000
13
b11 6
b10 E
1+
11
1'
#1630000
0'
#1640000
b100 6
b11 E
1'
#1650000
0'
#1660000
b101 6
b100 E
1'
#1670000
0'
#1680000
b110 6
b101 E
1'
#1690000
0'
#1700000
14
b111 6
b110 E
1'
#1710000
0'
#1720000
04
1C
13
b1000 -
b1000 /
b1000 9
b10101010 :
b0 6
b111 E
1'
#1730000
0'
#1740000
0C
1A
1>
0!
0"
b1 6
b1000 <
b1000 ?
b1000 G
b101010110 H
b0 E
1'
#1750000
0'
#1760000
b10 6
b1 E
00
1'
#1770000
0'
#1780000
13
b11 6
b10 E
0+
01
1'
#1790000
0'
#1800000
b100 6
b11 E
1'
#1810000
0'
#1820000
b101 6
b100 E
1'
#1830000
0'
#1840000
b110 6
b101 E
1'
#1850000
0'
#1860000
14
b111 6
b110 E
1'
#1870000
0'
#1880000
04
1C
13
b1001 -
b1001 /
b1001 9
b1010101 :
b0 6
b111 E
1'
#1890000
0'
#1900000
0C
1A
0>
1!
1"
b1 6
b1001 <
b1001 ?
b1001 G
b10101011 H
b0 E
1'
#1910000
0'
#1920000
b10 6
b1 E
10
1'
#1930000
0'
#1940000
13
b11 6
b10 E
1+
11
1'
#1950000
0'
#1960000
b100 6
b11 E
1'
#1970000
0'
#1980000
b101 6
b100 E
1'
#1990000
0'
#2000000
b110 6
b101 E
1'
#2010000
0'
#2020000
14
b111 6
b110 E
1'
#2030000
0'
#2040000
04
1C
03
b1010101 %
b1010101 ,
b1010101 8
07
b1010 -
b1010 /
b1010 9
b10101010 :
b0 6
b111 E
1'
#2050000
0'
#2060000
1$
0C
0A
02
b1010 <
b1010 ?
b1010 G
b101010101 H
b0 E
0F
1'
#2070000
0'
#2080000
1#
0@
1'
#2081000
1*
#2090000
0'
#2100000
1'
#2110000
0'
#2120000
1'
#2130000
0'
#2140000
1'
#2150000
0'
#2160000
1'
#2170000
0'
#2180000
1'
#2190000
0'
#2200000
1'
#2210000
0'
#2220000
1'
#2230000
0'
#2240000
1'
#2250000
0'
#2260000
1'
#2270000
0'
#2280000
1'
#2290000
0'
#2300000
1'
#2310000
0'
#2320000
1'
#2330000
1A
1=
1)
0'
#2340000
0#
0!
0"
1A
0=
1F
b101010100 H
b0 <
b0 ?
b0 G
1@
1'
#2350000
1A
0)
0'
#2360000
b1 E
00
1'
#2370000
0'
#2380000
13
1.
b10 E
0+
01
1'
#2390000
0'
#2400000
0$
13
0.
17
b0 -
b0 /
b0 9
12
b11 E
1'
#2410000
0'
#2420000
b1 6
b100 E
1'
#2430000
0'
#2440000
b10 6
b101 E
1'
#2450000
0'
#2460000
15
b11 6
b110 E
1'
#2470000
0'
#2480000
05
1C
13
b1 -
b1 /
b1 9
b0 6
b111 E
1'
#2490000
0'
#2500000
0C
1>
1A
1!
1"
b1 6
b1 <
b1 ?
b1 G
b101010101 H
b0 E
1'
#2510000
0'
#2520000
b10 6
b1 E
10
1'
#2530000
0'
#2540000
13
b11 6
b10 E
1+
11
1'
#2550000
0'
#2560000
b100 6
b11 E
1'
#2570000
0'
#2580000
b101 6
b100 E
1'
#2590000
0'
#2600000
b110 6
b101 E
1'
#2610000
0'
#2620000
14
b111 6
b110 E
1'
#2630000
0'
#2640000
04
1C
13
b10 -
b10 /
b10 9
b11010101 :
b0 6
b111 E
1'
#2650000
0'
#2660000
0C
1A
1>
0!
0"
b1 6
b10 <
b10 ?
b10 G
b110101010 H
b0 E
1'
#2670000
0'
#2680000
b10 6
b1 E
00
1'
#2690000
0'
#2700000
13
b11 6
b10 E
0+
01
1'
#2710000
0'
#2720000
b100 6
b11 E
1'
#2730000
0'
#2740000
b101 6
b100 E
1'
#2750000
0'
#2760000
b110 6
b101 E
1'
#2770000
0'
#2780000
14
b111 6
b110 E
1'
#2790000
0'
#2800000
04
1C
13
b11 -
b11 /
b11 9
b1101010 :
b0 6
b111 E
1'
#2810000
0'
#2820000
0C
1A
1>
1!
1"
b1 6
b11 <
b11 ?
b11 G
b11010101 H
b0 E
1'
#2830000
0'
#2840000
b10 6
b1 E
10
1'
#2850000
0'
#2860000
13
b11 6
b10 E
1+
11
1'
#2870000
0'
#2880000
b100 6
b11 E
1'
#2890000
0'
#2900000
b101 6
b100 E
1'
#2910000
0'
#2920000
b110 6
b101 E
1'
#2930000
0'
#2940000
14
b111 6
b110 E
1'
#2950000
0'
#2960000
04
1C
13
b100 -
b100 /
b100 9
b10110101 :
b0 6
b111 E
1'
#2970000
0'
#2980000
0C
1A
1>
0!
0"
b1 6
b100 <
b100 ?
b100 G
b101101010 H
b0 E
1'
#2990000
0'
#3000000
b10 6
b1 E
00
1'
#3010000
0'
#3020000
13
b11 6
b10 E
0+
01
1'
#3030000
0'
#3040000
b100 6
b11 E
1'
#3050000
0'
#3060000
b101 6
b100 E
1'
#3070000
0'
#3080000
b110 6
b101 E
1'
#3090000
0'
#3100000
14
b111 6
b110 E
1'
#3110000
0'
#3120000
04
1C
13
b101 -
b101 /
b101 9
b1011010 :
b0 6
b111 E
1'
#3130000
0'
#3140000
0C
1A
1>
1!
1"
b1 6
b101 <
b101 ?
b101 G
b10110101 H
b0 E
1'
#3150000
0'
#3160000
b10 6
b1 E
10
1'
#3170000
0'
#3180000
13
b11 6
b10 E
1+
11
1'
#3190000
0'
#3200000
b100 6
b11 E
1'
#3210000
0'
#3220000
b101 6
b100 E
1'
#3230000
0'
#3240000
b110 6
b101 E
1'
#3250000
0'
#3260000
14
b111 6
b110 E
1'
#3270000
0'
#3280000
04
1C
13
b110 -
b110 /
b110 9
b10101101 :
b0 6
b111 E
1'
#3290000
0'
#3300000
0C
1A
1>
0!
0"
b1 6
b110 <
b110 ?
b110 G
b101011010 H
b0 E
1'
#3310000
0'
#3320000
b10 6
b1 E
00
1'
#3330000
0'
#3340000
13
b11 6
b10 E
0+
01
1'
#3350000
0'
#3360000
b100 6
b11 E
1'
#3370000
0'
#3380000
b101 6
b100 E
1'
#3390000
0'
#3400000
b110 6
b101 E
1'
#3410000
0'
#3420000
14
b111 6
b110 E
1'
#3430000
0'
#3440000
04
1C
13
b111 -
b111 /
b111 9
b1010110 :
b0 6
b111 E
1'
#3450000
0'
#3460000
0C
1A
1>
1!
1"
b1 6
b111 <
b111 ?
b111 G
b10101101 H
b0 E
1'
#3470000
0'
#3480000
b10 6
b1 E
10
1'
#3490000
0'
#3500000
13
b11 6
b10 E
1+
11
1'
#3510000
0'
#3520000
b100 6
b11 E
1'
#3530000
0'
#3540000
b101 6
b100 E
1'
#3550000
0'
#3560000
b110 6
b101 E
1'
#3570000
0'
#3580000
14
b111 6
b110 E
1'
#3590000
0'
#3600000
04
1C
13
b1000 -
b1000 /
b1000 9
b10101011 :
b0 6
b111 E
1'
#3610000
0'
#3620000
0C
1A
1>
0!
0"
b1 6
b1000 <
b1000 ?
b1000 G
b101010110 H
b0 E
1'
#3630000
0'
#3640000
b10 6
b1 E
00
1'
#3650000
0'
#3660000
13
b11 6
b10 E
0+
01
1'
#3670000
0'
#3680000
b100 6
b11 E
1'
#3690000
0'
#3700000
b101 6
b100 E
1'
#3710000
0'
#3720000
b110 6
b101 E
1'
#3730000
0'
#3740000
14
b111 6
b110 E
1'
#3750000
0'
#3760000
04
1C
13
b1001 -
b1001 /
b1001 9
b1010101 :
b0 6
b111 E
1'
#3770000
0'
#3780000
0C
1A
0>
1!
1"
b1 6
b1001 <
b1001 ?
b1001 G
b10101011 H
b0 E
1'
#3790000
0'
#3800000
b10 6
b1 E
10
1'
#3810000
0'
#3820000
13
b11 6
b10 E
1+
11
1'
#3830000
0'
#3840000
b100 6
b11 E
1'
#3850000
0'
#3860000
b101 6
b100 E
1'
#3870000
0'
#3880000
b110 6
b101 E
1'
#3890000
0'
#3900000
14
b111 6
b110 E
1'
#3910000
0'
#3920000
04
1C
03
07
b1010 -
b1010 /
b1010 9
b10101010 :
b0 6
b111 E
1'
#3930000
0'
#3940000
1$
0C
0A
02
b1010 <
b1010 ?
b1010 G
b101010101 H
b0 E
0F
1'
#3950000
0'
#3960000
1#
0@
1'
#3961000
0*
#3970000
0'
#3980000
1'
#3990000
0'
#4000000
1'
#4010000
0'
#4020000
1'
#4030000
0'
#4040000
1'
#4050000
0'
#4060000
1'
#4070000
0'
#4080000
1'
#4090000
0'
#4100000
1'
#4110000
0'
#4120000
1'
#4130000
0'
#4140000
1'
#4150000
0'
#4160000
1'
#4170000
0'
#4180000
1'
#4190000
0'
#4200000
1'
#4210000
1A
1=
1)
0'
#4220000
0#
0!
0"
1A
0=
1F
b101010100 H
b0 <
b0 ?
b0 G
1@
1'
#4230000
1A
0)
0'
#4240000
b1 E
00
1'
#4250000
0'
#4260000
13
1.
b10 E
0+
01
1'
#4270000
0'
#4280000
0$
13
0.
17
b0 -
b0 /
b0 9
12
b11 E
1'
#4290000
0'
#4300000
b1 6
b100 E
1'
#4310000
0'
#4320000
b10 6
b101 E
1'
#4330000
0'
#4340000
15
b11 6
b110 E
1'
#4350000
0'
#4360000
05
1C
13
b1 -
b1 /
b1 9
b0 6
b111 E
1'
#4370000
0'
#4380000
0C
1>
1A
1!
1"
b1 6
b1 <
b1 ?
b1 G
b101010101 H
b0 E
1'
#4390000
0'
#4400000
b10 6
b1 E
10
1'
#4410000
0'
#4420000
13
b11 6
b10 E
1+
11
1'
#4430000
0'
#4440000
b100 6
b11 E
1'
#4450000
0'
#4460000
b101 6
b100 E
1'
#4470000
0'
#4480000
b110 6
b101 E
1'
#4490000
0'
#4500000
14
b111 6
b110 E
1'
#4510000
0'
#4520000
04
1C
13
b10 -
b10 /
b10 9
b11010101 :
b0 6
b111 E
1'
#4530000
0'
#4540000
0C
1A
1>
0!
0"
b1 6
b10 <
b10 ?
b10 G
b110101010 H
b0 E
1'
#4550000
0'
#4560000
b10 6
b1 E
00
1'
#4570000
0'
#4580000
13
b11 6
b10 E
0+
01
1'
#4590000
0'
#4600000
b100 6
b11 E
1'
#4610000
0'
#4620000
b101 6
b100 E
1'
#4630000
0'
#4640000
b110 6
b101 E
1'
#4650000
0'
#4660000
14
b111 6
b110 E
1'
#4670000
0'
#4680000
04
1C
13
b11 -
b11 /
b11 9
b1101010 :
b0 6
b111 E
1'
#4690000
0'
#4700000
0C
1A
1>
1!
1"
b1 6
b11 <
b11 ?
b11 G
b11010101 H
b0 E
1'
#4710000
0'
#4720000
b10 6
b1 E
10
1'
#4730000
0'
#4740000
13
b11 6
b10 E
1+
11
1'
#4750000
0'
#4760000
b100 6
b11 E
1'
#4770000
0'
#4780000
b101 6
b100 E
1'
#4790000
0'
#4800000
b110 6
b101 E
1'
#4810000
0'
#4820000
14
b111 6
b110 E
1'
#4830000
0'
