Icarus/ex6/myfulladder.v
/* reference referencedesigner.com */

`timescale 1ns / 100ps

`define ANSI_Style

`ifdef ANSI_Style
module fulladder #(parameter N = 8) (in1, in2, cin, sum, cout);
`else
module fulladder (in1, in2, cin, sum, cout);
parameter N = 8;
`endif

input wire [N-1:0] in1, in2;
input wire cin;
output wire [N-1:0] sum;
output wire cout;

wire [N:0] tempsum;

assign tempsum = {1'b0, in1} + {1'b0, in2} + cin;
assign sum = tempsum[N-1:0];
assign cout = tempsum[N];

endmodule

Icarus/ex6/testbench_top.v
/* reference referencedesigner.com */

`timescale 1ns / 100ps

module top;
parameter width = 8;

reg [width-1:0] input1;
reg [width-1:0] input2;
reg carryin;

wire [width-1:0] out;
wire carryout;

fulladder #(.N(width)) uut (
.in1(input1),
.in2(input2),
.cin(carryin),
.sum(out),
.cout(carryout)
);

initial begin
    $dumpfile("test.vcd");
    $dumpvars(0,top);
    input1 = 0;
    input2 = 0;
    carryin = 0;
    #20 input1 = 1;
    #20 input2 = 2;
    #20 input1 = 0;
    #20 carryin = 1;
    #20 input2 = 0;
    #20 input1 = 15; 
    #20 input2 = 15;
    #40;
    $dumpflush;
end //initial begin

initial begin
$monitor("time = %2d, CIN =%1b, IN1=%X, IN2=%X, COUT=%1b, OUT=%X", $time,carryin,input2,input1,carryout,out);
end

endmodule

Icarus/ex6/test.vcd
$date
	Mon Sep 07 15:40:38 2020
$end
$version
	Icarus Verilog
$end
$timescale
	100ps
$end
$scope module top $end
$var wire 8 ! out [7:0] $end
$var wire 1 " carryout $end
$var reg 1 # carryin $end
$var reg 8 $ input1 [7:0] $end
$var reg 8 % input2 [7:0] $end
$scope module uut $end
$var wire 1 # cin $end
$var wire 8 & in1 [7:0] $end
$var wire 8 ' in2 [7:0] $end
$var wire 9 ( tempsum [8:0] $end
$var wire 8 ) sum [7:0] $end
$var wire 1 " cout $end
$upscope $end
$upscope $end
$enddefinitions $end
#0
$dumpvars
b0 )
b0 (
b0 '
b0 &
b0 %
b0 $
0#
0"
b0 !
$end
#200
b1 !
b1 )
b1 (
b1 $
b1 &
#400
b11 !
b11 )
b11 (
b10 %
b10 '
#600
b10 !
b10 )
b10 (
b0 $
b0 &
#800
b11 !
b11 )
b11 (
1#
#1000
b1 !
b1 )
b1 (
b0 %
b0 '
#1200
b10000 !
b10000 )
b10000 (
b1111 $
b1111 &
#1400
b11111 !
b11111 )
b11111 (
b1111 %
b1111 '
